Workbook

Sheet Feature dictionary
B2: Feature dictionary
B6: Feature group | C6: Feature | D6: Usable for model 1
B7: Glassdoor | C7: review_id | D7: No
B8: Glassdoor | C8: summary | D8: No
B9: Glassdoor | C9: date | D9: No
B10: Glassdoor | C10: job_title | D10: No
B11: Glassdoor | C11: overall_rating | D11: No
B12: Glassdoor | C12: pros | D12: No
B13: Glassdoor | C13: cons | D13: No
B14: Glassdoor | C14: author_location | D14: No
B15: Glassdoor | C15: company | D15: No
B16: Glassdoor | C16: overall_rating_cat | D16: No
B17: Fill | C17: Company | D17: No
... B340: Sector OHE | C340: Sector_Transportation_ohe | D340: Yes

Sheet Execution planner
B2: Execution planner
B5: Execution groups
B7: Execution group | C7: Detail
B8: 1 | C8: Only string length features
B9: 2 | C9: All usable features (independent PCA per feature group)
B10: 3 | C10: Only features from NLP creation
B11: 4 | C11: Those created from NLP & JDI and ODI similarities
B12: 5 | C12: All usable features without PCA
B15: Execution list
B17: Execution ID | C17: Execution group | E17: Features to include | F17: PCA | G17: Model architecture | H17: Execution ID real | I17: Number of search iterations | J17: Train time | K17: Metric 1 | L17: Metric 1 train | M17: Metric 1 test | N17: Metric 2 | O17: Metric 2 train | P17: Metric 2 test
B18: =C18&"-"&D18 -> 1-1 | C18: 1 | D18: 1 | E18: String length features | F18: No | G18: Elasticnet | H18: 20260510_200916 | I18: 20 | J18: 0:00:10 | K18: MAPE | L18: 0.393578 | M18: 0.392581 | N18: MSE | O18: 1.264836 | P18: 1.255447
B19: =C19&"-"&D19 -> 1-2 | C19: 1 | D19: 2 | E19: String length features | F19: No | G19: KNN | H19: 20260510_200944 | I19: 40 | J19: 0:03:14 | K19: MAPE | L19: 0.333228 | M19: 0.339514 | N19: MSE | O19: 1.004385 | P19: 1.044247
B20: =C20&"-"&D20 -> 1-3 | C20: 1 | D20: 3 | E20: String length features | F20: No | G20: Decision tree | H20: 20260510_201349 | I20: 40 | J20: 0:00:19 | K20: MAPE | L20: 0.334303 | M20: 0.341116 | N20: MSE | O20: 1.03494 | P20: 1.073051
B21: =C21&"-"&D21 -> 1-4 | C21: 1 | D21: 4 | E21: String length features | F21: No | G21: Random forrest | H21: 20260511_161959 | I21: 40 | J21: 0:50:58 | K21: MAPE | L21: 0.272985 | M21: 0.332013 | N21: MSE | O21: 0.701743 | P21: 1.021916
B22: =C22&"-"&D22 -> 1-5 | C22: 1 | D22: 5 | E22: String length features | F22: No | G22: Support vector machine | H22: 20260517_195042 | I22: 5 | J22: 0:02:51 | K22: MAPE | L22: 0.437552 | M22: 0.436859 | N22: MSE | O22: 2.375026 | P22: 2.375184
B23: =C23&"-"&D23 -> 1-6 | C23: 1 | D23: 6 | E23: String length features | F23: No | G23: XG Boost | H23: 20260517_194228 | I23: 100 | J23: 0:05:17 | K23: MAPE | L23: 0.324062 | M23: 0.327767 | N23: MSE | O23: 0.975023 | P23: 0.997304
B24: =C24&"-"&D24 -> 2-1 | C24: 2 | D24: 1 | E24: All usable features | F24: Yes, 1 dim per feature group | G24: Elasticnet | H24: 20260517_201027 | I24: 20 | J24: 0:00:02 | K24: MAPE | L24: 0.394305 | M24: 0.393505 | N24: MSE | O24: 1.30538 | P24: 1.30063
B25: =C25&"-"&D25 -> 2-2 | C25: 2 | D25: =D24+1 -> 2 | E25: All usable features | F25: Yes, 5 dim per feature group | G25: Elasticnet | H25: 20260517_201050 | I25: 20 | J25: 0:00:04 | K25: MAPE | L25: 0.360784 | M25: 0.359239 | N25: MSE | O25: 1.134651 | P25: 1.124337
B26: =C26&"-"&D26 -> 2-3 | C26: 2 | D26: =D25+1 -> 3 | E26: All usable features | F26: Yes, 1 dim per every 5 dims in the feature group | G26: Elasticnet | H26: 20260517_201115 | I26: 20 | J26: 0:00:03 | K26: MAPE | L26: 0.388799 | M26: 0.387619 | N26: MSE | O26: 1.278544 | P26: 1.272891
B27: =C27&"-"&D27 -> 2-4 | C27: 2 | D27: =D26+1 -> 4 | E27: All usable features | F27: Yes, 1 dim per feature group | G27: KNN | H27: 20260517_201139 | I27: 40 | J27: 0:07:55 | K27: MAPE | L27: 0 | M27: 0.383584 | N27: MSE | O27: 0 | P27: 1.240026
B28: =C28&"-"&D28 -> 2-5 | C28: 2 | D28: =D27+1 -> 5 | E28: All usable features | F28: Yes, 5 dim per feature group | G28: KNN | H28: 20260517_202121 | I28: 40 | J28: 0:51:09 | K28: MAPE | L28: 0 | M28: 0.351768 | N28: MSE | O28: 0 | P28: 1.064118
B29: =C29&"-"&D29 -> 2-6 | C29: 2 | D29: =D28+1 -> 6 | E29: All usable features | F29: Yes, 1 dim per every 5 dims in the feature group | G29: KNN | H29: 20260517_211354 | I29: 40 | J29: 0:43:09 | K29: MAPE | L29: 0 | M29: 0.374058 | N29: MSE | O29: 0 | P29: 1.157778
B30: =C30&"-"&D30 -> 2-7 | C30: 2 | D30: =D29+1 -> 7 | E30: All usable features | F30: Yes, 1 dim per feature group | G30: Decision tree | H30: 20260517_220031 | I30: 40 | J30: 0:00:44 | K30: MAPE | L30: 0.366343 | M30: 0.37336 | N30: MSE | O30: 1.190765 | P30: 1.231122
B31: =C31&"-"&D31 -> 2-8 | C31: 2 | D31: =D30+1 -> 8 | E31: All usable features | F31: Yes, 5 dim per feature group | G31: Decision tree | H31: 20260517_220136 | I31: 40 | J31: 0:02:33 | K31: MAPE | L31: 0.314207 | M31: 0.324027 | N31: MSE | O31: 0.963927 | P31: 1.016488
B32: =C32&"-"&D32 -> 2-9 | C32: 2 | D32: =D31+1 -> 9 | E32: All usable features | F32: Yes, 1 dim per every 5 dims in the feature group | G32: Decision tree | H32: 20260517_220429 | I32: 40 | J32: 0:01:47 | K32: MAPE | L32: 0.349924 | M32: 0.361546 | N32: MSE | O32: 1.112656 | P32: 1.17793
B33: =C33&"-"&D33 -> 2-10 | C33: 2 | D33: =D32+1 -> 10 | E33: All usable features | F33: Yes, 1 dim per feature group | G33: Random forrest | H33: 20260517_220637 | I33: 40 | J33: 0:57:39 | K33: MAPE | L33: 0.271727 | M33: 0.368663 | N33: MSE | O33: 0.654659 | P33: 1.195577
B34: =C34&"-"&D34 -> 2-11 | C34: 2 | D34: =D33+1 -> 11 | E34: All usable features | F34: Yes, 5 dim per feature group | G34: Random forrest | H34: 20260517_230505 | I34: 40 | J34: 1:57:29 | K34: MAPE | L34: 0.149786 | M34: 0.31483 | N34: MSE | O34: 0.215859 | P34: 0.93373
B35: =C35&"-"&D35 -> 2-12 | C35: 2 | D35: =D34+1 -> 12 | E35: All usable features | F35: Yes, 1 dim per every 5 dims in the feature group | G35: Random forrest | H35: 20260518_010401 | I35: 40 | J35: 1:42:01 | K35: MAPE | L35: 0.244367 | M35: 0.345671 | N35: MSE | O35: 0.546105 | P35: 1.071256
B36: =C36&"-"&D36 -> 2-13 | C36: 2 | D36: =D35+1 -> 13 | E36: All usable features | F36: Yes, 1 dim per feature group | G36: Support vector machine | H36: 20260518_024652 | I36: 10 | J36: 0:14:53 | K36: MAPE | L36: 0.440141 | M36: 0.439662 | N36: MSE | O36: 2.05707 | P36: 2.055821
... B41: =C41&"-"&D41 -> 2-18 | C41: 2 | D41: =D40+1 -> 18 | E41: All usable features | F41: Yes, 1 dim per every 5 dims in the feature group | G41: XG Boost | H41: 20260518_040938 | I41: 100 | J41: 0:08:43 | K41: MAPE | L41: 0.284021 | M41: 0.334244 | N41: MSE | O41: 0.772715 | P41: 1.032178
B42: =C42&"-"&D42 -> 2-19 | C42: 2 | D42: 19 | E42: All usable features | F42: Yes, 1 dim per every 5 dims in the feature group | G42: XG Boost | H42: 20260518_041843 | I42: 100 | J42: 0:08:45 | K42: MAPE | L42: 0.284021 | M42: 0.334244 | N42: MSE | O42: 0.772715 | P42: 1.032178
B43: =C43&"-"&D43 -> 3-1 | C43: 3 | D43: 1 | E43: Only NLP from feature creation | F43: No | G43: Elasticnet | H43: 20260505_175409 | I43: 20 | J43: 0:01:58 | K43: MAPE | L43: 0.350015 | M43: 0.348817 | N43: MSE | O43: 1.082365 | P43: 1.074583
B44: =C44&"-"&D44 -> 3-2 | C44: 3 | D44: =D43+1 -> 2 | E44: Only NLP from feature creation | F44: Yes, 1 dim per feature group | G44: Elasticnet | H44: 20260505_175625 | I44: 20 | J44: 0:00:01 | K44: MAPE | L44: 0.394991 | M44: 0.394123 | N44: MSE | O44: 1.309452 | P44: 1.304614
B45: =C45&"-"&D45 -> 3-3 | C45: 3 | D45: =D44+1 -> 3 | E45: Only NLP from feature creation | F45: Yes, 5 dim per feature group | G45: Elasticnet | H45: 20260505_175643 | I45: 20 | J45: 0:00:01 | K45: MAPE | L45: 0.363749 | M45: 0.362255 | N45: MSE | O45: 1.150078 | P45: 1.140852
B46: =C46&"-"&D46 -> 3-4 | C46: 3 | D46: =D45+1 -> 4 | E46: Only NLP from feature creation | F46: Yes, 1 dim per every 5 dims in the feature group | G46: Elasticnet | H46: 20260505_175702 | I46: 20 | J46: 0:00:01 | K46: MAPE | L46: 0.389499 | M46: 0.388285 | N46: MSE | O46: 1.282504 | P46: 1.276769
B47: =C47&"-"&D47 -> 3-5 | C47: 3 | D47: =D46+1 -> 5 | E47: Only NLP from feature creation | F47: No | G47: KNN | H47: 20260505_175720 | I47: 40 | J47: 0:49:04 | K47: MAPE | L47: 8e-05 | M47: 0.353006 | N47: MSE | O47: 0.000238 | P47: 1.052704
B48: =C48&"-"&D48 -> 3-6 | C48: 3 | D48: =D47+1 -> 6 | E48: Only NLP from feature creation | F48: Yes, 1 dim per feature group | G48: KNN | H48: 20260505_185051 | I48: 40 | J48: 0:00:33 | K48: MAPE | L48: 0.371153 | M48: 0.37801 | N48: MSE | O48: 1.185957 | P48: 1.229518
B49: =C49&"-"&D49 -> 3-7 | C49: 3 | D49: =D48+1 -> 7 | E49: Only NLP from feature creation | F49: Yes, 5 dim per feature group | G49: KNN | H49: 20260505_185210 | I49: 40 | J49: 0:22:07 | K49: MAPE | L49: 8e-05 | M49: 0.341669 | N49: MSE | O49: 0.000238 | P49: 1.022662
B50: =C50&"-"&D50 -> 3-8 | C50: 3 | D50: =D49+1 -> 8 | E50: Only NLP from feature creation | F50: Yes, 1 dim per every 5 dims in the feature group | G50: KNN | H50: 20260505_191602 | I50: 40 | J50: 0:26:05 | K50: MAPE | L50: 8e-05 | M50: 0.366362 | N50: MSE | O50: 0.000238 | P50: 1.135547
B51: =C51&"-"&D51 -> 3-9 | C51: 3 | D51: =D50+1 -> 9 | E51: Only NLP from feature creation | F51: No | G51: Decision tree | H51: 20260505_200950 | I51: 40 | J51: 0:00:20 | K51: MAPE | L51: 0.30779 | M51: 0.317544 | N51: MSE | O51: 0.931431 | P51: 0.983428
B52: =C52&"-"&D52 -> 3-10 | C52: 3 | D52: =D51+1 -> 10 | E52: Only NLP from feature creation | F52: Yes, 1 dim per feature group | G52: Decision tree | H52: 20260505_201028 | I52: 40 | J52: 0:00:08 | K52: MAPE | L52: 0.366444 | M52: 0.373042 | N52: MSE | O52: 1.192031 | P52: 1.228582
B53: =C53&"-"&D53 -> 3-11 | C53: 3 | D53: =D52+1 -> 11 | E53: Only NLP from feature creation | F53: Yes, 5 dim per feature group | G53: Decision tree | H53: 20260505_201054 | I53: 40 | J53: 0:00:27 | K53: MAPE | L53: 0.314725 | M53: 0.324097 | N53: MSE | O53: 0.966437 | P53: 1.01636
B54: =C54&"-"&D54 -> 3-12 | C54: 3 | D54: =D53+1 -> 12 | E54: Only NLP from feature creation | F54: Yes, 1 dim per every 5 dims in the feature group | G54: Decision tree | H54: 20260505_201139 | I54: 40 | J54: 0:00:21 | K54: MAPE | L54: 0.34993 | M54: 0.361334 | N54: MSE | O54: 1.113381 | P54: 1.177157
B55: =C55&"-"&D55 -> 3-13 | C55: 3 | D55: =D54+1 -> 13 | E55: Only NLP from feature creation | F55: No | G55: Random forrest | H55: 20260506_111118 | I55: 40 | J55: 0:23:03 | K55: MAPE | L55: 0.18551 | M55: 0.309704 | N55: MSE | O55: 0.344677 | P55: 0.904102
... B66: =C66&"-"&D66 -> 3-24 | C66: 3 | D66: =D65+1 -> 24 | E66: Only NLP from feature creation | F66: Yes, 1 dim per every 5 dims in the feature group | G66: XG Boost | H66: 20260512_101531 | I66: 100 | J66: 0:07:09 | K66: MAPE | L66: 0.292058 | M66: 0.335591 | N66: MSE | O66: 0.811641 | P66: 1.038574
B67: =C67&"-"&D67 -> 4-1 | C67: 4 | D67: 1 | E67: Those created from NLP & JDI and ODI similarities | F67: No | G67: Elasticnet | H67: 20260518_043032 | I67: 20 | J67: 0:02:27 | K67: MAPE | L67: 0.350015 | M67: 0.348817 | N67: MSE | O67: 1.082365 | P67: 1.074583
B68: =C68&"-"&D68 -> 4-2 | C68: 4 | D68: =D67+1 -> 2 | E68: Those created from NLP & JDI and ODI similarities | F68: Yes, 1 dim per feature group | G68: Elasticnet | H68: 20260518_043319 | I68: 20 | J68: 0:00:01 | K68: MAPE | L68: 0.394991 | M68: 0.394123 | N68: MSE | O68: 1.309452 | P68: 1.304614
B69: =C69&"-"&D69 -> 4-3 | C69: 4 | D69: =D68+1 -> 3 | E69: Those created from NLP & JDI and ODI similarities | F69: Yes, 5 dim per feature group | G69: Elasticnet | H69: 20260518_043340 | I69: 20 | J69: 0:00:04 | K69: MAPE | L69: 0.363749 | M69: 0.362255 | N69: MSE | O69: 1.150078 | P69: 1.140852
B70: =C70&"-"&D70 -> 4-4 | C70: 4 | D70: =D69+1 -> 4 | E70: Those created from NLP & JDI and ODI similarities | F70: Yes, 1 dim per every 5 dims in the feature group | G70: Elasticnet | H70: 20260518_043404 | I70: 20 | J70: 0:00:04 | K70: MAPE | L70: 0.389499 | M70: 0.388285 | N70: MSE | O70: 1.282504 | P70: 1.276769
B71: =C71&"-"&D71 -> 4-5 | C71: 4 | D71: =D70+1 -> 5 | E71: Those created from NLP & JDI and ODI similarities | F71: No | G71: KNN | H71: 20260518_043427 | I71: 40 | J71: 2:00:44 | K71: MAPE | L71: 8e-05 | M71: 0.353006 | N71: MSE | O71: 0.000238 | P71: 1.052704
B72: =C72&"-"&D72 -> 4-6 | C72: 4 | D72: =D71+1 -> 6 | E72: Those created from NLP & JDI and ODI similarities | F72: Yes, 1 dim per feature group | G72: KNN | H72: 20260518_064623 | I72: 40 | J72: 0:01:37 | K72: MAPE | L72: 0.371153 | M72: 0.378009 | N72: MSE | O72: 1.185958 | P72: 1.229514
B73: =C73&"-"&D73 -> 4-7 | C73: 4 | D73: =D72+1 -> 7 | E73: Those created from NLP & JDI and ODI similarities | F73: Yes, 5 dim per feature group | G73: KNN | H73: 20260518_064838 | I73: 40 | J73: 0:43:12 | K73: MAPE | L73: 8e-05 | M73: 0.341669 | N73: MSE | O73: 0.000238 | P73: 1.022662
B74: =C74&"-"&D74 -> 4-8 | C74: 4 | D74: =D73+1 -> 8 | E74: Those created from NLP & JDI and ODI similarities | F74: Yes, 1 dim per every 5 dims in the feature group | G74: KNN | H74: 20260518_073524 | I74: 40 | J74: 1:35:33 | K74: MAPE | L74: 8e-05 | M74: 0.366362 | N74: MSE | O74: 0.000238 | P74: 1.13555
B75: =C75&"-"&D75 -> 4-9 | C75: 4 | D75: =D74+1 -> 9 | E75: Those created from NLP & JDI and ODI similarities | F75: No | G75: Decision tree | H75: 20260518_093109 | I75: 40 | J75: 0:01:15 | K75: MAPE | L75: 0.30779 | M75: 0.317544 | N75: MSE | O75: 0.931431 | P75: 0.983428
B76: =C76&"-"&D76 -> 4-10 | C76: 4 | D76: =D75+1 -> 10 | E76: Those created from NLP & JDI and ODI similarities | F76: Yes, 1 dim per feature group | G76: Decision tree | H76: 20260518_093243 | I76: 40 | J76: 0:00:37 | K76: MAPE | L76: 0.366444 | M76: 0.373042 | N76: MSE | O76: 1.192031 | P76: 1.228582
B77: =C77&"-"&D77 -> 4-11 | C77: 4 | D77: =D76+1 -> 11 | E77: Those created from NLP & JDI and ODI similarities | F77: Yes, 5 dim per feature group | G77: Decision tree | H77: 20260518_093340 | I77: 40 | J77: 0:02:02 | K77: MAPE | L77: 0.314725 | M77: 0.324097 | N77: MSE | O77: 0.966437 | P77: 1.01636
B78: =C78&"-"&D78 -> 4-12 | C78: 4 | D78: =D77+1 -> 12 | E78: Those created from NLP & JDI and ODI similarities | F78: Yes, 1 dim per every 5 dims in the feature group | G78: Decision tree | H78: 20260518_093601 | I78: 40 | J78: 0:01:32 | K78: MAPE | L78: 0.34993 | M78: 0.361334 | N78: MSE | O78: 1.113381 | P78: 1.177157
B79: =C79&"-"&D79 -> 4-13 | C79: 4 | D79: =D78+1 -> 13 | E79: Those created from NLP & JDI and ODI similarities | F79: No | G79: Random forrest | H79: 20260518_093753 | I79: 40 | J79: 0:45:17 | K79: MAPE | L79: 0.18551 | M79: 0.309704 | N79: MSE | O79: 0.344677 | P79: 0.904102
... B90: =C90&"-"&D90 -> 4-24 | C90: 4 | D90: =D89+1 -> 24 | E90: Those created from NLP & JDI and ODI similarities | F90: Yes, 1 dim per every 5 dims in the feature group | G90: XG Boost | H90: 20260518_171123 | I90: 100 | J90: 0:07:59 | K90: MAPE | L90: 0.292058 | M90: 0.335591 | N90: MSE | O90: 0.811641 | P90: 1.038574
B91: =C91&"-"&D91 -> 5-1 | C91: 5 | D91: 1 | E91: All usable features | F91: No | G91: Elasticnet | H91: 20260512_154119 | I91: 20 | J91: 0:02:11 | K91: MAPE | L91: 0.347514 | M91: 0.346273 | N91: MSE | O91: 1.06987 | P91: 1.061247
B92: =C92&"-"&D92 -> 5-2 | C92: 5 | D92: =D91+1 -> 2 | E92: All usable features | F92: No | G92: KNN | H92: 20260512_154347 | I92: 40 | J92: 1:56:23 | K92: MAPE | L92: 0 | M92: 0.362405 | N92: MSE | O92: 0 | P92: 1.082587
B93: =C93&"-"&D93 -> 5-3 | C93: 5 | D93: =D92+1 -> 3 | E93: All usable features | F93: No | G93: Decision tree | H93: 20260512_175117 | I93: 40 | J93: 0:01:25 | K93: MAPE | L93: 0.307364 | M93: 0.317718 | N93: MSE | O93: 0.929475 | P93: 0.983999
B94: =C94&"-"&D94 -> 5-4 | C94: 5 | D94: =D93+1 -> 4 | E94: All usable features | F94: No | G94: Random forrest | H94: 20260512_175258 | I94: 40 | J94: 0:49:53 | K94: MAPE | L94: 0.14846 | M94: 0.311171 | N94: MSE | O94: 0.211092 | P94: 0.904875
B95: =C95&"-"&D95 -> 5-5 | C95: 5 | D95: =D94+1 -> 5 | E95: All usable features | F95: No | G95: Support vector machine | H95: 20260512_184508 | I95: 10 | J95: 7:37:24 | K95: MAPE | L95: 0.367369 | M95: 0.374752 | N95: MSE | O95: 1.350301 | P95: 1.394155
B96: =C96&"-"&D96 -> 5-6 | C96: 5 | D96: =D95+1 -> 6 | E96: All usable features | F96: No | G96: XG Boost | H96: 20260513_022910 | I96: 100 | J96: 0:00:13 | K96: MAPE | L96: 0.265051 | M96: 0.292989 | N96: MSE | O96: 0.68064 | P96: 0.836843
B97: 6-1 | C97: 6 | D97: 1 | E97: String length features | F97: No | G97: LightGBM | H97: 20260514_161728 | I97: 100 | J97: 0:04:52 | K97: MAPE | L97: 0.323494 | M97: 0.327633 | N97: MSE | O97: 0.971199 | P97: 0.996196
B98: 6-2 | C98: 6 | D98: 2 | E98: All usable features | F98: Yes, 1 dim per feature group | G98: LightGBM | H98: 20260514_162241 | I98: 100 | J98: 0:04:59 | K98: MAPE | L98: 0.357453 | M98: 0.364173 | N98: MSE | O98: 1.129245 | P98: 1.168596
B99: 6-3 | C99: 6 | D99: 3 | E99: All usable features | F99: Yes, 5 dim per feature group | G99: LightGBM | H99: 20260514_162802 | I99: 100 | J99: 0:09:59 | K99: MAPE | L99: 0.273134 | M99: 0.301567 | N99: MSE | O99: 0.739775 | P99: 0.893274
B100: 6-4 | C100: 6 | D100: 4 | E100: All usable features | F100: Yes, 1 dim per every 5 dims in the feature group | G100: LightGBM | H100: 20260514_163827 | I100: 100 | J100: 0:08:12 | K100: MAPE | L100: 0.306089 | M100: 0.334404 | N100: MSE | O100: 0.877255 | P100: 1.032647
B101: 6-5 | C101: 6 | D101: 5 | E101: Only NLP from feature creation | F101: No | G101: LightGBM | H101: 20260514_164704 | I101: 100 | J101: 0:15:12 | K101: MAPE | L101: 0.268246 | M101: 0.292818 | N101: MSE | O101: 0.72638 | P101: 0.853852
B102: 6-6 | C102: 6 | D102: 6 | E102: Only NLP from feature creation | F102: Yes, 1 dim per feature group | G102: LightGBM | H102: 20260514_170242 | I102: 100 | J102: 0:04:30 | K102: MAPE | L102: 0.358045 | M102: 0.36548 | N102: MSE | O102: 1.132529 | P102: 1.177521
B103: 6-7 | C103: 6 | D103: 7 | E103: Only NLP from feature creation | F103: Yes, 5 dim per feature group | G103: LightGBM | H103: 20260514_170735 | I103: 100 | J103: 0:08:18 | K103: MAPE | L103: 0.291509 | M103: 0.303996 | N103: MSE | O103: 0.832633 | P103: 0.903406
B104: 6-8 | C104: 6 | D104: 8 | E104: Only NLP from feature creation | F104: Yes, 1 dim per every 5 dims in the feature group | G104: LightGBM | H104: 20260514_171617 | I104: 100 | J104: 0:07:28 | K104: MAPE | L104: 0.308304 | M104: 0.334824 | N104: MSE | O104: 0.890667 | P104: 1.037379
B105: 6-9 | C105: 6 | D105: 9 | E105: Those created from NLP & JDI and ODI similarities | F105: No | G105: LightGBM | H105: 20260514_172410 | I105: 100 | J105: 0:15:06 | K105: MAPE | L105: 0.268246 | M105: 0.292818 | N105: MSE | O105: 0.72638 | P105: 0.853852
B106: 6-10 | C106: 6 | D106: 10 | E106: Those created from NLP & JDI and ODI similarities | F106: Yes, 1 dim per feature group | G106: LightGBM | H106: 20260514_173942 | I106: 100 | J106: 0:04:27 | K106: MAPE | L106: 0.358045 | M106: 0.36548 | N106: MSE | O106: 1.132529 | P106: 1.177521
B107: 6-11 | C107: 6 | D107: 11 | E107: Those created from NLP & JDI and ODI similarities | F107: Yes, 5 dim per feature group | G107: LightGBM | H107: 20260514_174432 | I107: 100 | J107: 0:08:15 | K107: MAPE | L107: 0.291509 | M107: 0.303996 | N107: MSE | O107: 0.832633 | P107: 0.903406
B108: 6-12 | C108: 6 | D108: 12 | E108: Those created from NLP & JDI and ODI similarities | F108: Yes, 1 dim per every 5 dims in the feature group | G108: LightGBM | H108: 20260514_175311 | I108: 100 | J108: 0:07:31 | K108: MAPE | L108: 0.308304 | M108: 0.334824 | N108: MSE | O108: 0.890667 | P108: 1.037379
... B122: 6e-13 | C122: 6 | D122: 13 | E122: All usable features | F122: No | G122: LightGBM (Estandarizado) | H122: 20260518_190632 | I122: 100 | J122: 0:17:30 | K122: MAPE | L122: 0.264921 | M122: 0.291734 | N122: MSE | O122: 0.708196 | P122: 0.846401

Sheet Dashboard
B2: Dashboard
B5: General
B7: Execution name | C7: 20240512_070043 | E7: Metric 1 | F7: =INDEX('General inputs'!$B$5:$M$1048576, MATCH($C$7, 'General inputs'!$B$5:$B$1048576, 0), MATCH($E$7, 'General inputs'!$B$5:$M$5, 0)) -> #N/A | H7: Metric 2 | I7: =INDEX('General inputs'!$B$5:$M$1048576, MATCH($C$7, 'General inputs'!$B$5:$B$1048576, 0), MATCH($H$7, 'General inputs'!$B$5:$M$5, 0)) -> #N/A
B9: Train time | C9: =INDEX('General inputs'!$B$5:$M$1048576, MATCH($C$7, 'General inputs'!$B$5:$B$1048576, 0), MATCH($B$9, 'General inputs'!$B$5:$M$5, 0)) -> #N/A | E9: Metric 1 train | F9: =INDEX('General inputs'!$B$5:$M$1048576, MATCH($C$7, 'General inputs'!$B$5:$B$1048576, 0), MATCH($E$9, 'General inputs'!$B$5:$M$5, 0)) -> #N/A | H9: Metric 2 train | I9: =INDEX('General inputs'!$B$5:$M$1048576, MATCH($C$7, 'General inputs'!$B$5:$B$1048576, 0), MATCH($H$9, 'General inputs'!$B$5:$M$5, 0)) -> #N/A
B11: Model type | C11: =INDEX('General inputs'!$B$5:$M$1048576, MATCH($C$7, 'General inputs'!$B$5:$B$1048576, 0), MATCH($B$11, 'General inputs'!$B$5:$M$5, 0)) -> #N/A | E11: Metric 1 test | F11: =INDEX('General inputs'!$B$5:$M$1048576, MATCH($C$7, 'General inputs'!$B$5:$B$1048576, 0), MATCH($E$11, 'General inputs'!$B$5:$M$5, 0)) -> #N/A | H11: Metric 2 test | I11: =INDEX('General inputs'!$B$5:$M$1048576, MATCH($C$7, 'General inputs'!$B$5:$B$1048576, 0), MATCH($H$11, 'General inputs'!$B$5:$M$5, 0)) -> #N/A
B13: Number of folds | C13: =INDEX('General inputs'!$B$5:$M$1048576, MATCH($C$7, 'General inputs'!$B$5:$B$1048576, 0), MATCH($B$13, 'General inputs'!$B$5:$M$5, 0)) -> #N/A
B15: Number of search iterations | C15: =INDEX('General inputs'!$B$5:$M$1048576, MATCH($C$7, 'General inputs'!$B$5:$B$1048576, 0), MATCH($B$15, 'General inputs'!$B$5:$M$5, 0)) -> #N/A
B17: PCA | C17: =INDEX('General inputs'!$B$5:$M$1048576, MATCH($C$7, 'General inputs'!$B$5:$B$1048576, 0), MATCH($B$17, 'General inputs'!$B$5:$M$5, 0)) -> #N/A
B20: Predictions deepdive
D22: Train real | K22: Test predicted
D24: 1 | E24: 2 | F24: 3 | G24: 4 | H24: 5 | K24: 1 | L24: 2 | M24: 3 | N24: 4 | O24: 5
C25: =C26+1 -> 5 | D25: =COUNTIFS(_xlfn.ANCHORARRAY(Dropdowns!$F$9), Dashboard!D$24, Dropdowns!$H$9:$H$307, Dashboard!$C25) / COUNTA(_xlfn.ANCHORARRAY(Dropdowns!$F$9)) -> 0 | E25: =COUNTIFS(_xlfn.ANCHORARRAY(Dropdowns!$F$9), Dashboard!E$24, Dropdowns!$H$9:$H$307, Dashboard!$C25) / COUNTA(_xlfn.ANCHORARRAY(Dropdowns!$F$9)) -> 0 | F25: =COUNTIFS(_xlfn.ANCHORARRAY(Dropdowns!$F$9), Dashboard!F$24, Dropdowns!$H$9:$H$307, Dashboard!$C25) / COUNTA(_xlfn.ANCHORARRAY(Dropdowns!$F$9)) -> 0.0033444816 | G25: =COUNTIFS(_xlfn.ANCHORARRAY(Dropdowns!$F$9), Dashboard!G$24, Dropdowns!$H$9:$H$307, Dashboard!$C25) / COUNTA(_xlfn.ANCHORARRAY(Dropdowns!$F$9)) -> 0.033444816 | H25: =COUNTIFS(_xlfn.ANCHORARRAY(Dropdowns!$F$9), Dashboard!H$24, Dropdowns!$H$9:$H$307, Dashboard!$C25) / COUNTA(_xlfn.ANCHORARRAY(Dropdowns!$F$9)) -> 0.040133779 | J25: =C25 -> 5 | K25: =COUNTIFS(_xlfn.ANCHORARRAY(Dropdowns!$J$9), Dashboard!K$24, Dropdowns!$L$9:$L$307, Dashboard!$J25) / COUNTA(_xlfn.ANCHORARRAY(Dropdowns!$J$9)) -> 0 | L25: =COUNTIFS(_xlfn.ANCHORARRAY(Dropdowns!$J$9), Dashboard!L$24, Dropdowns!$L$9:$L$307, Dashboard!$J25) / COUNTA(_xlfn.ANCHORARRAY(Dropdowns!$J$9)) -> 0 | M25: =COUNTIFS(_xlfn.ANCHORARRAY(Dropdowns!$J$9), Dashboard!M$24, Dropdowns!$L$9:$L$307, Dashboard!$J25) / COUNTA(_xlfn.ANCHORARRAY(Dropdowns!$J$9)) -> 0.0066889632 | N25: =COUNTIFS(_xlfn.ANCHORARRAY(Dropdowns!$J$9), Dashboard!N$24, Dropdowns!$L$9:$L$307, Dashboard!$J25) / COUNTA(_xlfn.ANCHORARRAY(Dropdowns!$J$9)) -> 0.030100334 | O25: =COUNTIFS(_xlfn.ANCHORARRAY(Dropdowns!$J$9), Dashboard!O$24, Dropdowns!$L$9:$L$307, Dashboard!$J25) / COUNTA(_xlfn.ANCHORARRAY(Dropdowns!$J$9)) -> 0.066889632
C26: =C27+1 -> 4 | D26: =COUNTIFS(_xlfn.ANCHORARRAY(Dropdowns!$F$9), Dashboard!D$24, Dropdowns!$H$9:$H$307, Dashboard!$C26) / COUNTA(_xlfn.ANCHORARRAY(Dropdowns!$F$9)) -> 0.02006689 | E26: =COUNTIFS(_xlfn.ANCHORARRAY(Dropdowns!$F$9), Dashboard!E$24, Dropdowns!$H$9:$H$307, Dashboard!$C26) / COUNTA(_xlfn.ANCHORARRAY(Dropdowns!$F$9)) -> 0.030100334 | F26: =COUNTIFS(_xlfn.ANCHORARRAY(Dropdowns!$F$9), Dashboard!F$24, Dropdowns!$H$9:$H$307, Dashboard!$C26) / COUNTA(_xlfn.ANCHORARRAY(Dropdowns!$F$9)) -> 0.096989967 | G26: =COUNTIFS(_xlfn.ANCHORARRAY(Dropdowns!$F$9), Dashboard!G$24, Dropdowns!$H$9:$H$307, Dashboard!$C26) / COUNTA(_xlfn.ANCHORARRAY(Dropdowns!$F$9)) -> 0.23411371 | H26: =COUNTIFS(_xlfn.ANCHORARRAY(Dropdowns!$F$9), Dashboard!H$24, Dropdowns!$H$9:$H$307, Dashboard!$C26) / COUNTA(_xlfn.ANCHORARRAY(Dropdowns!$F$9)) -> 0.2173913 | J26: =C26 -> 4 | K26: =COUNTIFS(_xlfn.ANCHORARRAY(Dropdowns!$J$9), Dashboard!K$24, Dropdowns!$L$9:$L$307, Dashboard!$J26) / COUNTA(_xlfn.ANCHORARRAY(Dropdowns!$J$9)) -> 0.033444816 | L26: =COUNTIFS(_xlfn.ANCHORARRAY(Dropdowns!$J$9), Dashboard!L$24, Dropdowns!$L$9:$L$307, Dashboard!$J26) / COUNTA(_xlfn.ANCHORARRAY(Dropdowns!$J$9)) -> 0.043478261 | M26: =COUNTIFS(_xlfn.ANCHORARRAY(Dropdowns!$J$9), Dashboard!M$24, Dropdowns!$L$9:$L$307, Dashboard!$J26) / COUNTA(_xlfn.ANCHORARRAY(Dropdowns!$J$9)) -> 0.12040134 | N26: =COUNTIFS(_xlfn.ANCHORARRAY(Dropdowns!$J$9), Dashboard!N$24, Dropdowns!$L$9:$L$307, Dashboard!$J26) / COUNTA(_xlfn.ANCHORARRAY(Dropdowns!$J$9)) -> 0.20401338 | O26: =COUNTIFS(_xlfn.ANCHORARRAY(Dropdowns!$J$9), Dashboard!O$24, Dropdowns!$L$9:$L$307, Dashboard!$J26) / COUNTA(_xlfn.ANCHORARRAY(Dropdowns!$J$9)) -> 0.17391304
C27: =C28+1 -> 3 | D27: =COUNTIFS(_xlfn.ANCHORARRAY(Dropdowns!$F$9), Dashboard!D$24, Dropdowns!$H$9:$H$307, Dashboard!$C27) / COUNTA(_xlfn.ANCHORARRAY(Dropdowns!$F$9)) -> 0.02006689 | E27: =COUNTIFS(_xlfn.ANCHORARRAY(Dropdowns!$F$9), Dashboard!E$24, Dropdowns!$H$9:$H$307, Dashboard!$C27) / COUNTA(_xlfn.ANCHORARRAY(Dropdowns!$F$9)) -> 0.02006689 | F27: =COUNTIFS(_xlfn.ANCHORARRAY(Dropdowns!$F$9), Dashboard!F$24, Dropdowns!$H$9:$H$307, Dashboard!$C27) / COUNTA(_xlfn.ANCHORARRAY(Dropdowns!$F$9)) -> 0.070234114 | G27: =COUNTIFS(_xlfn.ANCHORARRAY(Dropdowns!$F$9), Dashboard!G$24, Dropdowns!$H$9:$H$307, Dashboard!$C27) / COUNTA(_xlfn.ANCHORARRAY(Dropdowns!$F$9)) -> 0.073578595 | H27: =COUNTIFS(_xlfn.ANCHORARRAY(Dropdowns!$F$9), Dashboard!H$24, Dropdowns!$H$9:$H$307, Dashboard!$C27) / COUNTA(_xlfn.ANCHORARRAY(Dropdowns!$F$9)) -> 0.050167224 | J27: =C27 -> 3 | K27: =COUNTIFS(_xlfn.ANCHORARRAY(Dropdowns!$J$9), Dashboard!K$24, Dropdowns!$L$9:$L$307, Dashboard!$J27) / COUNTA(_xlfn.ANCHORARRAY(Dropdowns!$J$9)) -> 0.02006689 | L27: =COUNTIFS(_xlfn.ANCHORARRAY(Dropdowns!$J$9), Dashboard!L$24, Dropdowns!$L$9:$L$307, Dashboard!$J27) / COUNTA(_xlfn.ANCHORARRAY(Dropdowns!$J$9)) -> 0.033444816 | M27: =COUNTIFS(_xlfn.ANCHORARRAY(Dropdowns!$J$9), Dashboard!M$24, Dropdowns!$L$9:$L$307, Dashboard!$J27) / COUNTA(_xlfn.ANCHORARRAY(Dropdowns!$J$9)) -> 0.076923077 | N27: =COUNTIFS(_xlfn.ANCHORARRAY(Dropdowns!$J$9), Dashboard!N$24, Dropdowns!$L$9:$L$307, Dashboard!$J27) / COUNTA(_xlfn.ANCHORARRAY(Dropdowns!$J$9)) -> 0.066889632 | O27: =COUNTIFS(_xlfn.ANCHORARRAY(Dropdowns!$J$9), Dashboard!O$24, Dropdowns!$L$9:$L$307, Dashboard!$J27) / COUNTA(_xlfn.ANCHORARRAY(Dropdowns!$J$9)) -> 0.033444816
C28: =C29+1 -> 2 | D28: =COUNTIFS(_xlfn.ANCHORARRAY(Dropdowns!$F$9), Dashboard!D$24, Dropdowns!$H$9:$H$307, Dashboard!$C28) / COUNTA(_xlfn.ANCHORARRAY(Dropdowns!$F$9)) -> 0.030100334 | E28: =COUNTIFS(_xlfn.ANCHORARRAY(Dropdowns!$F$9), Dashboard!E$24, Dropdowns!$H$9:$H$307, Dashboard!$C28) / COUNTA(_xlfn.ANCHORARRAY(Dropdowns!$F$9)) -> 0.030100334 | F28: =COUNTIFS(_xlfn.ANCHORARRAY(Dropdowns!$F$9), Dashboard!F$24, Dropdowns!$H$9:$H$307, Dashboard!$C28) / COUNTA(_xlfn.ANCHORARRAY(Dropdowns!$F$9)) -> 0.016722408 | G28: =COUNTIFS(_xlfn.ANCHORARRAY(Dropdowns!$F$9), Dashboard!G$24, Dropdowns!$H$9:$H$307, Dashboard!$C28) / COUNTA(_xlfn.ANCHORARRAY(Dropdowns!$F$9)) -> 0.0033444816 | H28: =COUNTIFS(_xlfn.ANCHORARRAY(Dropdowns!$F$9), Dashboard!H$24, Dropdowns!$H$9:$H$307, Dashboard!$C28) / COUNTA(_xlfn.ANCHORARRAY(Dropdowns!$F$9)) -> 0 | J28: =C28 -> 2 | K28: =COUNTIFS(_xlfn.ANCHORARRAY(Dropdowns!$J$9), Dashboard!K$24, Dropdowns!$L$9:$L$307, Dashboard!$J28) / COUNTA(_xlfn.ANCHORARRAY(Dropdowns!$J$9)) -> 0.036789298 | L28: =COUNTIFS(_xlfn.ANCHORARRAY(Dropdowns!$J$9), Dashboard!L$24, Dropdowns!$L$9:$L$307, Dashboard!$J28) / COUNTA(_xlfn.ANCHORARRAY(Dropdowns!$J$9)) -> 0.023411371 | M28: =COUNTIFS(_xlfn.ANCHORARRAY(Dropdowns!$J$9), Dashboard!M$24, Dropdowns!$L$9:$L$307, Dashboard!$J28) / COUNTA(_xlfn.ANCHORARRAY(Dropdowns!$J$9)) -> 0.0033444816 | N28: =COUNTIFS(_xlfn.ANCHORARRAY(Dropdowns!$J$9), Dashboard!N$24, Dropdowns!$L$9:$L$307, Dashboard!$J28) / COUNTA(_xlfn.ANCHORARRAY(Dropdowns!$J$9)) -> 0.010033445 | O28: =COUNTIFS(_xlfn.ANCHORARRAY(Dropdowns!$J$9), Dashboard!O$24, Dropdowns!$L$9:$L$307, Dashboard!$J28) / COUNTA(_xlfn.ANCHORARRAY(Dropdowns!$J$9)) -> 0.0033444816
C29: 1 | D29: =COUNTIFS(_xlfn.ANCHORARRAY(Dropdowns!$F$9), Dashboard!D$24, Dropdowns!$H$9:$H$307, Dashboard!$C29) / COUNTA(_xlfn.ANCHORARRAY(Dropdowns!$F$9)) -> 0.010033445 | E29: =COUNTIFS(_xlfn.ANCHORARRAY(Dropdowns!$F$9), Dashboard!E$24, Dropdowns!$H$9:$H$307, Dashboard!$C29) / COUNTA(_xlfn.ANCHORARRAY(Dropdowns!$F$9)) -> 0 | F29: =COUNTIFS(_xlfn.ANCHORARRAY(Dropdowns!$F$9), Dashboard!F$24, Dropdowns!$H$9:$H$307, Dashboard!$C29) / COUNTA(_xlfn.ANCHORARRAY(Dropdowns!$F$9)) -> 0 | G29: =COUNTIFS(_xlfn.ANCHORARRAY(Dropdowns!$F$9), Dashboard!G$24, Dropdowns!$H$9:$H$307, Dashboard!$C29) / COUNTA(_xlfn.ANCHORARRAY(Dropdowns!$F$9)) -> 0 | H29: =COUNTIFS(_xlfn.ANCHORARRAY(Dropdowns!$F$9), Dashboard!H$24, Dropdowns!$H$9:$H$307, Dashboard!$C29) / COUNTA(_xlfn.ANCHORARRAY(Dropdowns!$F$9)) -> 0 | J29: =C29 -> 1 | K29: =COUNTIFS(_xlfn.ANCHORARRAY(Dropdowns!$J$9), Dashboard!K$24, Dropdowns!$L$9:$L$307, Dashboard!$J29) / COUNTA(_xlfn.ANCHORARRAY(Dropdowns!$J$9)) -> 0.0066889632 | L29: =COUNTIFS(_xlfn.ANCHORARRAY(Dropdowns!$J$9), Dashboard!L$24, Dropdowns!$L$9:$L$307, Dashboard!$J29) / COUNTA(_xlfn.ANCHORARRAY(Dropdowns!$J$9)) -> 0.0033444816 | M29: =COUNTIFS(_xlfn.ANCHORARRAY(Dropdowns!$J$9), Dashboard!M$24, Dropdowns!$L$9:$L$307, Dashboard!$J29) / COUNTA(_xlfn.ANCHORARRAY(Dropdowns!$J$9)) -> 0.0033444816 | N29: =COUNTIFS(_xlfn.ANCHORARRAY(Dropdowns!$J$9), Dashboard!N$24, Dropdowns!$L$9:$L$307, Dashboard!$J29) / COUNTA(_xlfn.ANCHORARRAY(Dropdowns!$J$9)) -> 0 | O29: =COUNTIFS(_xlfn.ANCHORARRAY(Dropdowns!$J$9), Dashboard!O$24, Dropdowns!$L$9:$L$307, Dashboard!$J29) / COUNTA(_xlfn.ANCHORARRAY(Dropdowns!$J$9)) -> 0
B63: Hyperparameter deepdive
B65: Hyperparameter | C65: n_estimators

Sheet Inputs >>>

Sheet General inputs
B2: General inputs
B5: Execution name | C5: Model type | D5: PCA | E5: Number of search iterations | F5: Number of folds | G5: Train time | H5: Metric 1 | I5: Metric 1 train | J5: Metric 1 test | K5: Metric 2 | L5: Metric 2 train | M5: Metric 2 test | N5: xxx | O5: Check
B6: 20260427_181736 | C6: elasticnet | D6: No | E6: 13 | F6: 5 | G6: 0:00:17.401253 | H6: MAPE | I6: 0.39357844 | J6: 0.39258057 | K6: MSE | L6: 1.2648363 | M6: 1.2554474 | O6: =IF(COUNTIFS($B:$B, B6), "OK", "ERROR") -> OK
B7: 20260427_181817 | C7: elasticnet | D7: Yes | E7: 13 | F7: 5 | G7: 0:00:01.405923 | H7: MAPE | I7: 0.38768022 | J7: 0.38665351 | K7: MSE | L7: 1.2707759 | M7: 1.2651896 | O7: =IF(COUNTIFS($B:$B, B7), "OK", "ERROR") -> OK
B8: 20260427_181844 | C8: elasticnet | D8: Yes | E8: 13 | F8: 5 | G8: 0:00:21.709849 | H8: MAPE | I8: 0.3188203 | J8: 0.31726548 | K8: MSE | L8: 0.94561314 | M8: 0.93654474 | O8: =IF(COUNTIFS($B:$B, B8), "OK", "ERROR") -> OK
B9: 20260427_181932 | C9: elasticnet | D9: Yes | E9: 13 | F9: 5 | G9: 0:00:13.639408 | H9: MAPE | I9: 0.32776883 | J9: 0.32730336 | K9: MSE | L9: 0.98759443 | M9: 0.98485883 | O9: =IF(COUNTIFS($B:$B, B9), "OK", "ERROR") -> OK
B10: 20260427_182011 | C10: elasticnet | D10: No | E10: 13 | F10: 5 | G10: 0:06:52.260709 | H10: MAPE | I10: 0.32494821 | J10: 0.32335531 | K10: MSE | L10: 0.97166755 | M10: 0.96458195 | O10: =IF(COUNTIFS($B:$B, B10), "OK", "ERROR") -> OK
B11: 20260427_182729 | C11: elasticnet | D11: Yes | E11: 13 | F11: 5 | G11: 0:00:00.873514 | H11: MAPE | I11: 0.39398793 | J11: 0.39305208 | K11: MSE | L11: 1.3070702 | M11: 1.3019481 | O11: =IF(COUNTIFS($B:$B, B11), "OK", "ERROR") -> OK
B12: 20260427_182755 | C12: elasticnet | D12: Yes | E12: 13 | F12: 5 | G12: 0:00:02.276957 | H12: MAPE | I12: 0.35182604 | J12: 0.34985911 | K12: MSE | L12: 1.0962028 | M12: 1.0851924 | O12: =IF(COUNTIFS($B:$B, B12), "OK", "ERROR") -> OK
B13: 20260427_182824 | C13: elasticnet | D13: Yes | E13: 13 | F13: 5 | G13: 0:00:04.035521 | H13: MAPE | I13: 0.36839915 | J13: 0.36746158 | K13: MSE | L13: 1.1774077 | M13: 1.1734015 | O13: =IF(COUNTIFS($B:$B, B13), "OK", "ERROR") -> OK
B14: 20260427_182853 | C14: elasticnet | D14: No | E14: 13 | F14: 5 | G14: 0:07:50.813873 | H14: MAPE | I14: 0.29383479 | J14: 0.2927413 | K14: MSE | L14: 0.83558398 | M14: 0.83011712 | O14: =IF(COUNTIFS($B:$B, B14), "OK", "ERROR") -> OK
B15: 20260427_183709 | C15: elasticnet | D15: Yes | E15: 13 | F15: 5 | G15: 0:00:00.835714 | H15: MAPE | I15: 0.39110276 | J15: 0.39017205 | K15: MSE | L15: 1.2872962 | M15: 1.2830434 | O15: =IF(COUNTIFS($B:$B, B15), "OK", "ERROR") -> OK
B16: 20260427_183734 | C16: elasticnet | D16: Yes | E16: 13 | F16: 5 | G16: 0:00:02.509612 | H16: MAPE | I16: 0.3216888 | J16: 0.32007848 | K16: MSE | L16: 0.95935081 | M16: 0.95070873 | O16: =IF(COUNTIFS($B:$B, B16), "OK", "ERROR") -> OK
B17: 20260427_183801 | C17: elasticnet | D17: Yes | E17: 13 | F17: 5 | G17: 0:00:04.654697 | H17: MAPE | I17: 0.32987974 | J17: 0.32923259 | K17: MSE | L17: 0.99697193 | M17: 0.99434618 | O17: =IF(COUNTIFS($B:$B, B17), "OK", "ERROR") -> OK
B18: 20260427_183830 | C18: elasticnet | D18: No | E18: 13 | F18: 5 | G18: 0:18:56.420782 | H18: MAPE | I18: 0.29121445 | J18: 0.2903663 | K18: MSE | L18: 0.82350807 | M18: 0.81797462 | O18: =IF(COUNTIFS($B:$B, B18), "OK", "ERROR") -> OK
B19: 20260427_215558 | C19: xgboost | D19: No | E19: 100 | F19: 5 | G19: 0:30:51.608411 | H19: MAPE | I19: 0.3207 | J19: 0.327 | K19: MSE | L19: 0.9597 | M19: 0.9969 | O19: =IF(B19="", "", IF(COUNTIFS($B:$B, B19), "OK", "ERROR")) -> OK
B20: 20260427_222714 | C20: xgboost | D20: Yes | E20: 100 | F20: 5 | G20: 0:15:58.122559 | H20: MAPE | I20: 0.3327 | J20: 0.3517 | K20: MSE | L20: 1.0033 | M20: 1.1111 | O20: =IF(B20="", "", IF(COUNTIFS($B:$B, B20), "OK", "ERROR")) -> OK
B21: 20260427_224837 | C21: xgboost | D21: Yes | E21: 100 | F21: 5 | G21: 0:46:22.477607 | H21: MAPE | I21: 0.2519 | J21: 0.2769 | K21: MSE | L21: 0.6536 | M21: 0.7775 | O21: =IF(B21="", "", IF(COUNTIFS($B:$B, B21), "OK", "ERROR")) -> OK
B22: 20260427_233525 | C22: xgboost | D22: Yes | E22: 100 | F22: 5 | G22: 0:25:54.997431 | H22: MAPE | I22: 0.2355 | J22: 0.2873 | K22: MSE | L22: 0.5721 | M22: 0.8229 | O22: =IF(B22="", "", IF(COUNTIFS($B:$B, B22), "OK", "ERROR")) -> OK
B23: 20260428_000146 | C23: xgboost | D23: No | E23: 100 | F23: 5 | G23: 0:42:20.614810 | H23: MAPE | I23: 0.2386 | J23: 0.2741 | K23: MSE | L23: 0.5988 | M23: 0.7687 | O23: =IF(B23="", "", IF(COUNTIFS($B:$B, B23), "OK", "ERROR")) -> OK
B24: 20260428_004431 | C24: xgboost | D24: Yes | E24: 100 | F24: 5 | G24: 0:07:09.743930 | H24: MAPE | I24: 0.3481 | J24: 0.3617 | K24: MSE | L24: 1.088 | M24: 1.1662 | O24: =IF(B24="", "", IF(COUNTIFS($B:$B, B24), "OK", "ERROR")) -> OK
B25: 20260428_005205 | C25: xgboost | D25: Yes | E25: 100 | F25: 5 | G25: 0:11:51.596028 | H25: MAPE | I25: 0.2735 | J25: 0.2949 | K25: MSE | L25: 0.7492 | M25: 0.8625 | O25: =IF(B25="", "", IF(COUNTIFS($B:$B, B25), "OK", "ERROR")) -> OK
B26: 20260428_010422 | C26: xgboost | D26: Yes | E26: 100 | F26: 5 | G26: 0:17:27.777915 | H26: MAPE | I26: 0.2639 | J26: 0.3149 | K26: MSE | L26: 0.6857 | M26: 0.949 | O26: =IF(B26="", "", IF(COUNTIFS($B:$B, B26), "OK", "ERROR")) -> OK
B27: 20260428_012215 | C27: xgboost | D27: No | E27: 100 | F27: 5 | G27: 0:52:51.357916 | H27: MAPE | I27: 0.2169 | J27: 0.2578 | K27: MSE | L27: 0.5115 | M27: 0.6986 | O27: =IF(B27="", "", IF(COUNTIFS($B:$B, B27), "OK", "ERROR")) -> OK
B28: 20260428_021531 | C28: xgboost | D28: Yes | E28: 100 | F28: 5 | G28: 0:07:20.944371 | H28: MAPE | I28: 0.344 | J28: 0.3596 | K28: MSE | L28: 1.0641 | M28: 1.1535 | O28: =IF(B28="", "", IF(COUNTIFS($B:$B, B28), "OK", "ERROR")) -> OK
B29: 20260428_022316 | C29: xgboost | D29: Yes | E29: 100 | F29: 5 | G29: 0:13:08.996127 | H29: MAPE | I29: 0.2584 | J29: 0.2807 | K29: MSE | L29: 0.6849 | M29: 0.7984 | O29: =IF(B29="", "", IF(COUNTIFS($B:$B, B29), "OK", "ERROR")) -> OK
B30: 20260428_023650 | C30: xgboost | D30: Yes | E30: 100 | F30: 5 | G30: 0:19:27.074065 | H30: MAPE | I30: 0.2653 | J30: 0.2928 | K30: MSE | L30: 0.7004 | M30: 0.8422 | O30: =IF(B30="", "", IF(COUNTIFS($B:$B, B30), "OK", "ERROR")) -> OK
... B45: 20260420_182012 | C45: xgboost | D45: Yes | E45: 100 | F45: 5 | G45: 0:38:30.159807 | H45: MAPE | I45: 0.212 | J45: 0.2875 | K45: MSE | L45: 0.4711 | M45: 0.8176 | O45: =IF(B45="", "", IF(COUNTIFS($B:$B, B45), "OK", "ERROR")) -> OK
B46: 20260428_220454 | C46: random_forest | D46: No | E46: 50 | F46: 5 | G46: 0:33:16.034946 | H46: MAPE | I46: 0.2694 | J46: 0.3317 | K46: MSE | L46: 0.693 | M46: 1.0195
B47: 20260428_223839 | C47: random_forest | D47: Yes | E47: 50 | F47: 5 | G47: 1:45:38.750272 | H47: MAPE | I47: 0.2301 | J47: 0.3628 | K47: MSE | L47: 0.468 | M47: 1.1519
B48: 20260429_002455 | C48: random_forest | D48: Yes | E48: 50 | F48: 5 | G48: 6:14:07.333198 | H48: MAPE | I48: 0.1501 | J48: 0.2919 | K48: MSE | L48: 0.2253 | M48: 0.8319
B49: 20260429_063939 | C49: random_forest | D49: Yes | E49: 50 | F49: 5 | G49: 8:45:57.088049 | H49: MAPE | I49: 0.1367 | J49: 0.312 | K49: MSE | L49: 0.1755 | M49: 0.8988

Sheet Train prediction inputs
B2: Train prediction inputs
B5: Real_20240511_133758 | C5: Predicted_20240511_133758 | D5: Real_20240511_165954 | E5: Predicted_20240511_165954 | F5: Real_20240511_174018 | G5: Predicted_20240511_174018 | H5: Real_20240512_070043 | I5: Predicted_20240512_070043 | J5: Real_20240519_212952 | K5: Predicted_20240519_212952 | L5: Real_20240519_214228 | M5: Predicted_20240519_214228 | N5: Real_20240525_195654 | O5: Predicted_20240525_195654 | P5: Real_20240525_214508 | Q5: Predicted_20240525_214508 | R5: Real_20240526_062912 | S5: Predicted_20240526_062912 | T5: Real_20240526_190924 | U5: Predicted_20240526_190924 | V5: Real_20241020_205600 | W5: Predicted_20241020_205600 | X5: Real_20240604_084257 | Y5: Predicted_20240604_084257 | Z5: Real_20240615_175916 | AA5: Predicted_20240615_175916 | AB5: Real_20241019_194000 | AC5: Predicted_20241019_194000 | AD5: Real_20241022_071500 | AE5: Predicted_20241022_071500
B6: 3 | C6: 3.6386099 | D6: 3 | E6: 3.64 | F6: 3 | G6: 3.6235866 | H6: 3 | I6: 3.3647306 | J6: 3 | K6: 3.6386099 | L6: 3 | M6: 3.8313864 | N6: 3 | O6: 3.9439729 | P6: 3 | Q6: 3.818503 | R6: 3 | S6: 4.1140028 | T6: 3 | U6: 3 | V6: 4 | W6: 3.8742507 | X6: 3 | Y6: 3.9672666 | Z6: 3 | AA6: 4.0877614 | AB6: 3 | AC6: 3.3959167 | AD6: 3 | AE6: 3.3984167
B7: 5 | C7: 4.2773779 | D7: 5 | E7: 4.38 | F7: 5 | G7: 4.2837511 | H7: 5 | I7: 4.3741765 | J7: 5 | K7: 4.2773779 | L7: 5 | M7: 4.6177242 | N7: 5 | O7: 3.7930803 | P7: 5 | Q7: 4.4966345 | R7: 5 | S7: 4.1691866 | T7: 5 | U7: 5 | V7: 5 | W7: 3.3504708 | X7: 5 | Y7: 3.7115523 | Z7: 5 | AA7: 3.6829927 | AB7: 5 | AC7: 4.8341667 | AD7: 5 | AE7: 4.6722381
B8: 3 | C8: 3.3935215 | D8: 3 | E8: 3.16 | F8: 3 | G8: 2.8209815 | H8: 3 | I8: 2.808288 | J8: 3 | K8: 3.3935215 | L8: 3 | M8: 3.3430637 | N8: 3 | O8: 3.3603408 | P8: 3 | Q8: 3.3736181 | R8: 3 | S8: 3.6503677 | T8: 3 | U8: 3 | V8: 3 | W8: 3.324692 | X8: 3 | Y8: 3.3999833 | Z8: 3 | AA8: 3.0626771 | AB8: 3 | AC8: 3.0954167 | AD8: 3 | AE8: 3.1783571
B9: 3 | C9: 3.7842062 | D9: 3 | E9: 4.02 | F9: 3 | G9: 4.098925 | H9: 3 | I9: 4.2254453 | J9: 3 | K9: 3.7842062 | L9: 3 | M9: 4.2791703 | N9: 3 | O9: 4.2200997 | P9: 3 | Q9: 3.3291964 | R9: 3 | S9: 3.7755841 | T9: 3 | U9: 3 | V9: 5 | W9: 3.345372 | X9: 3 | Y9: 3.8848847 | Z9: 3 | AA9: 4.2996306 | AB9: 3 | AC9: 3.270131 | AD9: 3 | AE9: 3.3513654
B10: 4 | C10: 3.7536319 | D10: 4 | E10: 3.77 | F10: 4 | G10: 4.0118971 | H10: 4 | I10: 4.0832624 | J10: 4 | K10: 3.7536319 | L10: 4 | M10: 3.8599418 | N10: 4 | O10: 3.8757481 | P10: 4 | Q10: 4.1081305 | R10: 4 | S10: 4.0294752 | T10: 4 | U10: 4 | V10: 2 | W10: 3.4894013 | X10: 4 | Y10: 4.3084538 | Z10: 4 | AA10: 4.2756467 | AB10: 4 | AC10: 4.11125 | AD10: 4 | AE10: 4.1610952
B11: 3 | C11: 3.8449129 | D11: 3 | E11: 4.17 | F11: 3 | G11: 4.0685013 | H11: 3 | I11: 4.1902246 | J11: 3 | K11: 3.8449129 | L11: 3 | M11: 4.2975956 | N11: 3 | O11: 3.1342773 | P11: 3 | Q11: 3.2911644 | R11: 3 | S11: 3.6338001 | T11: 3 | U11: 3 | V11: 5 | W11: 4.6307502 | X11: 3 | Y11: 3.0201265 | Z11: 3 | AA11: 2.7910361 | AB11: 3 | AC11: 3.2643182 | AD11: 3 | AE11: 3.13375
B12: 2 | C12: 2.7905947 | D12: 2 | E12: 2.16 | F12: 2 | G12: 2.3221084 | H12: 2 | I12: 2.1649487 | J12: 2 | K12: 2.7905947 | L12: 2 | M12: 2.035488 | N12: 2 | O12: 3.4779526 | P12: 2 | Q12: 2.7250104 | R12: 2 | S12: 2.9282259 | T12: 2 | U12: 2 | V12: 1 | W12: 2.3013661 | X12: 2 | Y12: 2.6878518 | Z12: 2 | AA12: 2.8932223 | AB12: 2 | AC12: 1.9576861 | AD12: 2 | AE12: 2.1036667
B13: 5 | C13: 3.7184848 | D13: 5 | E13: 4.53 | F13: 5 | G13: 4.2531863 | H13: 5 | I13: 4.359283 | J13: 5 | K13: 3.7184848 | L13: 5 | M13: 3.8599418 | N13: 5 | O13: 4.2594197 | P13: 5 | Q13: 3.256287 | R13: 5 | S13: 3.559698 | T13: 5 | U13: 5 | V13: 1 | W13: 1.7232678 | X13: 5 | Y13: 4.3345037 | Z13: 5 | AA13: 4.3341761 | AB13: 5 | AC13: 4.5503333 | AD13: 5 | AE13: 4.4669286
B14: 4 | C14: 4.1716572 | D14: 4 | E14: 4.43 | F14: 4 | G14: 4.7028503 | H14: 4 | I14: 4.762563 | J14: 4 | K14: 4.1716572 | L14: 4 | M14: 4.5788177 | N14: 4 | O14: 4.3647176 | P14: 4 | Q14: 4.4246626 | R14: 4 | S14: 4.8045878 | T14: 4 | U14: 4 | V14: 1 | W14: 2.5662246 | X14: 4 | Y14: 4.1271536 | Z14: 4 | AA14: 4.2045217 | AB14: 4 | AC14: 4.1727381 | AD14: 4 | AE14: 4.12
B15: 4 | C15: 3.9057279 | D15: 4 | E15: 4.41 | F15: 4 | G15: 4.2988495 | H15: 4 | I15: 4.499189 | J15: 4 | K15: 3.9057279 | L15: 4 | M15: 4.1486228 | N15: 4 | O15: 4.3959245 | P15: 4 | Q15: 4.2400432 | R15: 4 | S15: 4.4111359 | T15: 4 | U15: 4 | V15: 3 | W15: 3.6815944 | X15: 4 | Y15: 4.1120539 | Z15: 4 | AA15: 4.123611 | AB15: 4 | AC15: 4.1445476 | AD15: 4 | AE15: 4.0255238
B16: 2 | C16: 3.6898798 | D16: 2 | E16: 3.86 | F16: 2 | G16: 3.7711691 | H16: 2 | I16: 3.660352 | J16: 2 | K16: 3.6898798 | L16: 2 | M16: 3.8313864 | N16: 2 | O16: 3.4714457 | P16: 2 | Q16: 3.0063749 | R16: 2 | S16: 2.8364845 | T16: 2 | U16: 2 | V16: 5 | W16: 4.6824937 | X16: 2 | Y16: 3.4318543 | Z16: 2 | AA16: 3.4966161 | AB16: 2 | AC16: 2.4837937 | AD16: 2 | AE16: 2.4301151
B17: 3 | C17: 3.4106041 | D17: 3 | E17: 3.03 | F17: 3 | G17: 2.9086682 | H17: 3 | I17: 2.7960148 | J17: 3 | K17: 3.4106041 | L17: 3 | M17: 2.8082988 | N17: 3 | O17: 3.3738165 | P17: 3 | Q17: 3.2973195 | R17: 3 | S17: 3.4740742 | T17: 3 | U17: 3 | V17: 3 | W17: 3.3885305 | X17: 3 | Y17: 3.392805 | Z17: 3 | AA17: 3.5219939 | AB17: 3 | AC17: 2.9353929 | AD17: 3 | AE17: 3.138254
... B304: 5 | C304: 3.7762565 | D304: 5 | E304: 3.6 | F304: 5 | G304: 3.6934821 | H304: 5 | I304: 3.457445 | J304: 5 | K304: 3.7762565 | L304: 5 | M304: 3.7552812 | N304: 5 | O304: 4.4691099 | P304: 5 | Q304: 4.5014975 | R304: 5 | S304: 4.6867815 | T304: 5 | U304: 5 | V304: 3 | W304: 3.8002918 | X304: 5 | Y304: 4.4921902 | Z304: 5 | AA304: 4.5340614 | AB304: 5 | AC304: 4.7736667 | AD304: 5 | AE304: 4.612619

Sheet Test prediction inputs
B2: Test prediction inputs
B5: Real_20240511_133758 | C5: Predicted_20240511_133758 | D5: Real_20240511_165954 | E5: Predicted_20240511_165954 | F5: Real_20240511_174018 | G5: Predicted_20240511_174018 | H5: Real_20240512_070043 | I5: Predicted_20240512_070043 | J5: Real_20240519_212952 | K5: Predicted_20240519_212952 | L5: Real_20240519_214228 | M5: Predicted_20240519_214228 | N5: Real_20240525_195654 | O5: Predicted_20240525_195654 | P5: Real_20240525_214508 | Q5: Predicted_20240525_214508 | R5: Real_20240526_062912 | S5: Predicted_20240526_062912 | T5: Real_20240526_190924 | U5: Predicted_20240526_190924 | V5: Real_20241020_205600 | W5: Predicted_20241020_205600 | X5: Real_20240604_084257 | Y5: Predicted_20240604_084257 | Z5: Real_20240615_175916 | AA5: Predicted_20240615_175916 | AB5: Real_20241019_194000 | AC5: Predicted_20241019_194000 | AD5: Real_20241022_071500 | AE5: Predicted_20241022_071500
B6: 4 | C6: 3.8202929 | D6: 4 | E6: 3.91 | F6: 4 | G6: 3.8812899 | H6: 4 | I6: 3.891651 | J6: 4 | K6: 3.8202929 | L6: 4 | M6: 3.8313864 | N6: 4 | O6: 4.0081329 | P6: 4 | Q6: 4.1710977 | R6: 4 | S6: 4.2965295 | T6: 4 | U6: 4.3606402 | V6: 3 | W6: 3.5067329 | X6: 4 | Y6: 4.1932084 | Z6: 4 | AA6: 4.0823898 | AB6: 4 | AC6: 4.4274643 | AD6: 4 | AE6: 4.543881
B7: 3 | C7: 3.6050643 | D7: 3 | E7: 3.74 | F7: 3 | G7: 3.5116268 | H7: 3 | I7: 3.5741134 | J7: 3 | K7: 3.6050643 | L7: 3 | M7: 3.6448673 | N7: 3 | O7: 4.1605115 | P7: 3 | Q7: 4.2227544 | R7: 3 | S7: 4.2299231 | T7: 3 | U7: 4.1981282 | V7: 4 | W7: 3.8201149 | X7: 3 | Y7: 4.194567 | Z7: 3 | AA7: 4.2884016 | AB7: 3 | AC7: 3.9832778 | AD7: 3 | AE7: 4.0230833
B8: 3 | C8: 3.4555794 | D8: 3 | E8: 3.12 | F8: 3 | G8: 2.964796 | H8: 3 | I8: 3.0231738 | J8: 3 | K8: 3.4555794 | L8: 3 | M8: 3.4573991 | N8: 3 | O8: 3.5770759 | P8: 3 | Q8: 3.7517945 | R8: 3 | S8: 3.0100157 | T8: 3 | U8: 3.6760856 | V8: 3 | W8: 3.2440376 | X8: 3 | Y8: 3.6128801 | Z8: 3 | AA8: 3.5367332 | AB8: 3 | AC8: 3.2378492 | AD8: 3 | AE8: 3.566127
B9: 2 | C9: 3.4273689 | D9: 2 | E9: 2.67 | F9: 2 | G9: 2.4797962 | H9: 2 | I9: 2.3481338 | J9: 2 | K9: 3.4273689 | L9: 2 | M9: 2.25 | N9: 2 | O9: 3.442096 | P9: 2 | Q9: 3.1202646 | R9: 2 | S9: 2.9332466 | T9: 2 | U9: 3.5710571 | V9: 3 | W9: 3.3499682 | X9: 2 | Y9: 3.5451447 | Z9: 2 | AA9: 2.1600335 | AB9: 2 | AC9: 2.9283918 | AD9: 2 | AE9: 3.863131
B10: 3 | C10: 3.7110572 | D10: 3 | E10: 3.85 | F10: 3 | G10: 3.7922571 | H10: 3 | I10: 3.8366833 | J10: 3 | K10: 3.7110572 | L10: 3 | M10: 3.8313864 | N10: 3 | O10: 2.4308453 | P10: 3 | Q10: 2.1148287 | R10: 3 | S10: 2.3477825 | T10: 3 | U10: 2.6602248 | V10: 4 | W10: 4.1965756 | X10: 3 | Y10: 2.4669323 | Z10: 3 | AA10: 2.1396565 | AB10: 3 | AC10: 2.270873 | AD10: 3 | AE10: 2.6413333
B11: 2 | C11: 3.5641173 | D11: 2 | E11: 3.32 | F11: 2 | G11: 3.1827449 | H11: 2 | I11: 3.008226 | J11: 2 | K11: 3.5641173 | L11: 2 | M11: 3.5845455 | N11: 2 | O11: 4.0231403 | P11: 2 | Q11: 3.2341768 | R11: 2 | S11: 3.5723085 | T11: 2 | U11: 3.9742058 | V11: 4 | W11: 3.8921814 | X11: 2 | Y11: 3.9149497 | Z11: 2 | AA11: 3.5141613 | AB11: 2 | AC11: 3.2576548 | AD11: 2 | AE11: 3.3577619
B12: 5 | C12: 3.5338097 | D12: 5 | E12: 3.63 | F12: 5 | G12: 3.3787875 | H12: 5 | I12: 3.31209 | J12: 5 | K12: 3.5338097 | L12: 5 | M12: 3.6072559 | N12: 5 | O12: 3.6029294 | P12: 5 | Q12: 3.9808091 | R12: 5 | S12: 3.9115594 | T12: 5 | U12: 3.2822758 | V12: 2 | W12: 3.2690833 | X12: 5 | Y12: 4.017876 | Z12: 5 | AA12: 3.4676695 | AB12: 5 | AC12: 4.0875952 | AD12: 5 | AE12: 4.0324603
B13: 4 | C13: 3.8289966 | D13: 4 | E13: 3.9 | F13: 4 | G13: 3.7258705 | H13: 4 | I13: 3.6984987 | J13: 4 | K13: 3.8289966 | L13: 4 | M13: 3.7592975 | N13: 4 | O13: 3.9974977 | P13: 4 | Q13: 4.0145018 | R13: 4 | S13: 3.9034044 | T13: 4 | U13: 3.9377857 | V13: 3 | W13: 3.6504071 | X13: 4 | Y13: 3.9340994 | Z13: 4 | AA13: 3.7397459 | AB13: 4 | AC13: 3.9589127 | AD13: 4 | AE13: 4.2236548
B14: 1 | C14: 3.8423784 | D14: 1 | E14: 4.31 | F14: 1 | G14: 4.5554723 | H14: 1 | I14: 4.3758984 | J14: 1 | K14: 3.8423784 | L14: 1 | M14: 4.6670435 | N14: 1 | O14: 2.7956008 | P14: 1 | Q14: 3.3929464 | R14: 1 | S14: 3.5909223 | T14: 1 | U14: 3.0596414 | V14: 3 | W14: 3.4887819 | X14: 1 | Y14: 2.2434757 | Z14: 1 | AA14: 2.5764546 | AB14: 1 | AC14: 3.5522738 | AD14: 1 | AE14: 3.1350397
B15: 4 | C15: 3.316916 | D15: 4 | E15: 3.06 | F15: 4 | G15: 2.8894402 | H15: 4 | I15: 2.8832324 | J15: 4 | K15: 3.316916 | L15: 4 | M15: 2.7190427 | N15: 4 | O15: 3.8785765 | P15: 4 | Q15: 3.2747444 | R15: 4 | S15: 3.2683903 | T15: 4 | U15: 3.8957415 | V15: 2 | W15: 2.5661595 | X15: 4 | Y15: 3.569648 | Z15: 4 | AA15: 3.4743898 | AB15: 4 | AC15: 3.2018214 | AD15: 4 | AE15: 2.8709048
B16: 2 | C16: 3.8865867 | D16: 2 | E16: 2.58 | F16: 2 | G16: 2.7330265 | H16: 2 | I16: 2.8674903 | J16: 2 | K16: 3.8865867 | L16: 2 | M16: 2.6029685 | N16: 2 | O16: 3.5532243 | P16: 2 | Q16: 2.9987763 | R16: 2 | S16: 3.2397011 | T16: 2 | U16: 4.099957 | V16: 5 | W16: 3.4035027 | X16: 2 | Y16: 3.9592147 | Z16: 2 | AA16: 4.1714916 | AB16: 2 | AC16: 2.9137024 | AD16: 2 | AE16: 3.3714762
B17: 5 | C17: 3.5835659 | D17: 5 | E17: 3.32 | F17: 5 | G17: 3.3373167 | H17: 5 | I17: 3.249207 | J17: 5 | K17: 3.5835659 | L17: 5 | M17: 3.9747959 | N17: 5 | O17: 3.3719061 | P17: 5 | Q17: 3.3736952 | R17: 5 | S17: 3.5331964 | T17: 5 | U17: 4.0214011 | V17: 4 | W17: 2.6588585 | X17: 5 | Y17: 3.1926371 | Z17: 5 | AA17: 3.138778 | AB17: 5 | AC17: 3.3847976 | AD17: 5 | AE17: 3.6442976
... B304: 4 | C304: 4.1689489 | D304: 4 | E304: 4.68 | F304: 4 | G304: 4.6530294 | H304: 4 | I304: 4.551512 | J304: 4 | K304: 4.1689489 | L304: 4 | M304: 4.6756757 | N304: 4 | O304: 4.0019654 | P304: 4 | Q304: 4.7291638 | R304: 4 | S304: 4.4768432 | T304: 4 | U304: 4.1684068 | V304: 2 | W304: 3.1441658 | X304: 4 | Y304: 4.4253749 | Z304: 4 | AA304: 4.3557725 | AB304: 4 | AC304: 4.8575 | AD304: 4 | AE304: 4.5961667

Sheet Execution deepdive inputs
B2: Execution deepdive inputs
O5: =Dropdowns!V9 -> subsample | Q5: =Dropdowns!V10 -> reg_lambda | S5: =Dropdowns!V11 -> reg_alpha | U5: =Dropdowns!V12 -> n_estimators | W5: =Dropdowns!V13 -> max_depth | Y5: =Dropdowns!V14 -> learning_rate | AA5: =Dropdowns!V15 -> gamma
B6: mean_fit_time | C6: std_fit_time | D6: mean_score_time | E6: std_score_time | F6: mean_test_score | G6: std_test_score | H6: rank_test_score | I6: split0_test_score | J6: split1_test_score | K6: split2_test_score | L6: split3_test_score | M6: split4_test_score | N6: Execution name | O6: param_0_name | P6: param_0 | Q6: param_1_name | R6: param_1 | S6: param_2_name | T6: param_2 | U6: param_3_name | V6: param_3 | W6: param_4_name | X6: param_4 | Y6: param_5_name | Z6: param_5 | AA6: param_6_name | AB6: param_6 | AC6: param_7_name | AD6: param_7
B7: 0.11757774 | C7: 0.013130948 | D7: 0.0060269833 | E7: 0.0022993424 | F7: -1.2088904 | G7: 0.0036520767 | H7: 6 | I7: -1.2126441 | J7: -1.209008 | K7: -1.2042656 | L7: -1.2131986 | M7: -1.2053359 | N7: 20240511_133758 | O7: max_iter | P7: 10000 | Q7: l1_ratio | R7: 0.7 | S7: alpha | T7: 0.4
B8: 0.063955307 | C8: 0.0080042826 | D8: 0.0067355156 | E8: 0.002777763 | F8: -1.2407202 | G8: 0.0038419033 | H8: 9 | I8: -1.2445136 | J8: -1.24081 | K8: -1.2363734 | L8: -1.2454466 | M8: -1.2364576 | N8: 20240511_133758 | O8: max_iter | P8: 10000 | Q8: l1_ratio | R8: 0.4 | S8: alpha | T8: 10
B9: 0.056131458 | C9: 0.00094269574 | D9: 0.0050855637 | E9: 0.0016529804 | F9: -1.2407202 | G9: 0.0038419033 | H9: 9 | I9: -1.2445136 | J9: -1.24081 | K9: -1.2363734 | L9: -1.2454466 | M9: -1.2364576 | N9: 20240511_133758 | O9: max_iter | P9: 10000 | Q9: l1_ratio | R9: 0.6 | S9: alpha | T9: 3
B10: 132.31876 | C10: 2.3343749 | D10: 0.016927671 | E10: 0.011333501 | F10: -1.1242264 | G10: 0.0054273458 | H10: 1 | I10: -1.1256806 | J10: -1.1175315 | K10: -1.121457 | L10: -1.1337357 | M10: -1.122727 | N10: 20240511_133758 | O10: max_iter | P10: 10000 | Q10: l1_ratio | R10: 0.4 | S10: alpha | T10: 0
B11: 0.079356956 | C11: 0.0087315358 | D11: 0.010981703 | E11: 0.0056505891 | F11: -1.2407202 | G11: 0.0038419033 | H11: 9 | I11: -1.2445136 | J11: -1.24081 | K11: -1.2363734 | L11: -1.2454466 | M11: -1.2364576 | N11: 20240511_133758 | O11: max_iter | P11: 10000 | Q11: l1_ratio | R11: 0.9 | S11: alpha | T11: 7
B12: 0.088186741 | C12: 0.017834808 | D12: 0.00542593 | E12: 0.001301495 | F12: -1.2407202 | G12: 0.0038419033 | H12: 9 | I12: -1.2445136 | J12: -1.24081 | K12: -1.2363734 | L12: -1.2454466 | M12: -1.2364576 | N12: 20240511_133758 | O12: max_iter | P12: 10000 | Q12: l1_ratio | R12: 0.7 | S12: alpha | T12: 100
B13: 0.11624236 | C13: 0.020466935 | D13: 0.0058285713 | E13: 0.001233948 | F13: -1.2407202 | G13: 0.0038419033 | H13: 9 | I13: -1.2445136 | J13: -1.24081 | K13: -1.2363734 | L13: -1.2454466 | M13: -1.2364576 | N13: 20240511_133758 | O13: max_iter | P13: 10000 | Q13: l1_ratio | R13: 1 | S13: alpha | T13: 1
B14: 0.15358934 | C14: 0.014253321 | D14: 0.0075437069 | E14: 0.0012699446 | F14: -1.1869071 | G14: 0.0033811385 | H14: 4 | I14: -1.1899963 | J14: -1.186324 | K14: -1.1819767 | L14: -1.1912839 | M14: -1.1849547 | N14: 20240511_133758 | O14: max_iter | P14: 10000 | Q14: l1_ratio | R14: 0.1 | S14: alpha | T14: 1
B15: 140.9623 | C15: 2.3132508 | D15: 0.010442591 | E15: 0.0015699735 | F15: -1.2378429 | G15: 0.0038168188 | H15: 8 | I15: -1.2416234 | J15: -1.2379162 | K15: -1.2334675 | L15: -1.2425344 | M15: -1.233673 | N15: 20240511_133758 | O15: max_iter | P15: 10000 | Q15: l1_ratio | R15: 0 | S15: alpha | T15: 100
B16: 0.14353743 | C16: 0.0078513208 | D16: 0.014439726 | E16: 0.0052051941 | F16: -1.2407202 | G16: 0.0038419033 | H16: 9 | I16: -1.2445136 | J16: -1.24081 | K16: -1.2363734 | L16: -1.2454466 | M16: -1.2364576 | N16: 20240511_133758 | O16: max_iter | P16: 10000 | Q16: l1_ratio | R16: 0.3 | S16: alpha | T16: 10
B17: 0.31494284 | C17: 0.019666489 | D17: 0.012017584 | E17: 0.0021717036 | F17: -1.1607875 | G17: 0.0038384522 | H17: 2 | I17: -1.1628157 | J17: -1.1584063 | K17: -1.1556886 | L17: -1.1669064 | M17: -1.1601206 | N17: 20240511_133758 | O17: max_iter | P17: 10000 | Q17: l1_ratio | R17: 0.1 | S17: alpha | T17: 0.4
B18: 0.16139569 | C18: 0.021825733 | D18: 0.014596987 | E18: 0.0042061939 | F18: -1.2407202 | G18: 0.0038419033 | H18: 9 | I18: -1.2445136 | J18: -1.24081 | K18: -1.2363734 | L18: -1.2454466 | M18: -1.2364576 | N18: 20240511_133758 | O18: max_iter | P18: 10000 | Q18: l1_ratio | R18: 0.3 | S18: alpha | T18: 100
... B26: 0.1421103 | C26: 0.0098734473 | D26: 0.01237855 | E26: 0.0024261606 | F26: -1.2407202 | G26: 0.0038419033 | H26: 9 | I26: -1.2445136 | J26: -1.24081 | K26: -1.2363734 | L26: -1.2454466 | M26: -1.2364576 | N26: 20240511_133758 | O26: max_iter | P26: 10000 | Q26: l1_ratio | R26: 0.3 | S26: alpha | T26: 2
B27: 0.6176259 | C27: 0.022231686 | D27: 18.243211 | E27: 0.593494 | F27: -1.1004474 | G27: 0.0032924785 | H27: 32 | I27: -1.1007661 | J27: -1.0961128 | K27: -1.0982185 | L27: -1.1058984 | M27: -1.1012414 | N27: 20240511_165954 | O27: weights | P27: distance | Q27: p | R27: 4 | S27: n_neighbors | T27: 7
B28: 0.59535327 | C28: 0.01766772 | D28: 18.121282 | E28: 0.41597511 | F28: -1.1004259 | G28: 0.0033810528 | H28: 31 | I28: -1.1003111 | J28: -1.0962335 | K28: -1.0980025 | L28: -1.1061413 | M28: -1.1014409 | N28: 20240511_165954 | O28: weights | P28: distance | Q28: p | R28: 5 | S28: n_neighbors | T28: 7
B29: 0.61082668 | C29: 0.019483848 | D29: 15.822286 | E29: 0.22275492 | F29: -1.0473143 | G29: 0.0025199255 | H29: 12 | I29: -1.047328 | J29: -1.044301 | K29: -1.0459214 | L29: -1.0518646 | M29: -1.0471565 | N29: 20240511_165954 | O29: weights | P29: distance | Q29: p | R29: 2 | S29: n_neighbors | T29: 100
B30: 0.59868708 | C30: 0.040387792 | D30: 11.509895 | E30: 0.19241501 | F30: -1.0548515 | G30: 0.002370642 | H30: 18 | I30: -1.054908 | J30: -1.0521086 | K30: -1.0534287 | L30: -1.059154 | M30: -1.0546583 | N30: 20240511_165954 | O30: weights | P30: distance | Q30: p | R30: 1 | S30: n_neighbors | T30: 30
B31: 0.6049242 | C31: 0.060111838 | D31: 19.062078 | E31: 0.37328925 | F31: -1.1005189 | G31: 0.003196574 | H31: 33 | I31: -1.1000502 | J31: -1.0966125 | K31: -1.0986785 | L31: -1.1061671 | M31: -1.1010863 | N31: 20240511_165954 | O31: weights | P31: distance | Q31: p | R31: 3 | S31: n_neighbors | T31: 7
B32: 0.59456887 | C32: 0.019850804 | D32: 22.419053 | E32: 1.1693369 | F32: -1.0604505 | G32: 0.0031942772 | H32: 21 | I32: -1.061325 | J32: -1.0553936 | K32: -1.0588474 | L32: -1.0649825 | M32: -1.0617038 | N32: 20240511_165954 | O32: weights | P32: uniform | Q32: p | R32: 5 | S32: n_neighbors | T32: 9
B33: 0.66979218 | C33: 0.078816281 | D33: 30.162787 | E33: 0.90694379 | F33: -1.0392618 | G33: 0.0025145735 | H33: 11 | I33: -1.0392153 | J33: -1.0354072 | K33: -1.0385259 | L33: -1.0432331 | M33: -1.0399275 | N33: 20240511_165954 | O33: weights | P33: uniform | Q33: p | R33: 5 | S33: n_neighbors | T33: 16
B34: 0.74109774 | C34: 0.034409518 | D34: 29.795417 | E34: 0.67640144 | F34: -1.0689524 | G34: 0.0026772601 | H34: 23 | I34: -1.0685603 | J34: -1.0658203 | K34: -1.0677347 | L34: -1.0738874 | M34: -1.068759 | N34: 20240511_165954 | O34: weights | P34: distance | Q34: p | R34: 5 | S34: n_neighbors | T34: 14
B35: 0.8523232 | C35: 0.14044271 | D35: 17.57252 | E35: 0.3604201 | F35: -1.0500998 | G35: 0.002425403 | H35: 15 | I35: -1.0501406 | J35: -1.0470189 | K35: -1.0491163 | L35: -1.0544416 | M35: -1.0497818 | N35: 20240511_165954 | O35: weights | P35: distance | Q35: p | R35: 1 | S35: n_neighbors | T35: 50
B36: 0.80492926 | C36: 0.11153297 | D36: 30.083779 | E36: 0.44407361 | F36: -1.0690336 | G36: 0.002712008 | H36: 24 | I36: -1.0688129 | J36: -1.0660117 | K36: -1.0673911 | L36: -1.0740222 | M36: -1.0689303 | N36: 20240511_165954 | O36: weights | P36: distance | Q36: p | R36: 4 | S36: n_neighbors | T36: 14
B37: 0.82880912 | C37: 0.11324268 | D37: 40.350167 | E37: 1.0344808 | F37: -1.0535335 | G37: 0.002810495 | H37: 17 | I37: -1.0534957 | J37: -1.049896 | K37: -1.0521327 | L37: -1.0584607 | M37: -1.0536821 | N37: 20240511_165954 | O37: weights | P37: distance | Q37: p | R37: 5 | S37: n_neighbors | T37: 30
B38: 0.80940585 | C38: 0.16411334 | D38: 35.626182 | E38: 0.88988625 | F38: -1.0339945 | G38: 0.0025268437 | H38: 9 | I38: -1.0344359 | J38: -1.0304493 | K38: -1.0325598 | L38: -1.0381082 | M38: -1.0344195 | N38: 20240511_165954 | O38: weights | P38: uniform | Q38: p | R38: 4 | S38: n_neighbors | T38: 20
... B66: 0.75927987 | C66: 0.035149728 | D66: 65.315226 | E66: 2.5107805 | F66: -1.0238332 | G66: 0.0023729774 | H66: 2 | I66: -1.0245083 | J66: -1.0203064 | K66: -1.0224531 | L66: -1.0274327 | M66: -1.0244653 | N66: 20240511_165954 | O66: weights | P66: uniform | Q66: p | R66: 3 | S66: n_neighbors | T66: 100
B67: 49.339199 | C67: 0.75169884 | D67: 0.80978422 | E67: 0.023866152 | F67: -1.0828253 | G67: 0.0025734095 | H67: 35 | I67: -1.0853123 | J67: -1.0799473 | K67: -1.0807367 | L67: -1.0864324 | M67: -1.0816979 | N67: 20240511_174018 | O67: n_estimators | P67: 200 | Q67: min_samples_split | R67: 2 | S67: max_depth | T67: 3
B68: 188.384 | C68: 5.3329479 | D68: 2.7425947 | E68: 0.23048763 | F68: -1.0094463 | G68: 0.0031964147 | H68: 3 | I68: -1.0098127 | J68: -1.0044334 | K68: -1.0079531 | L68: -1.0140562 | M68: -1.0109761 | N68: 20240511_174018 | O68: n_estimators | P68: 150 | Q68: min_samples_split | R68: 100 | S68: max_depth | T68: 57
B69: 266.47697 | C69: 3.1218582 | D69: 3.3718261 | E69: 0.15700911 | F69: -1.0153099 | G69: 0.0030579968 | H69: 13 | I69: -1.0150451 | J69: -1.0107077 | K69: -1.0141628 | L69: -1.0200643 | M69: -1.0165695 | N69: 20240511_174018 | O69: n_estimators | P69: 150 | Q69: min_samples_split | R69: 25 | S69: max_depth | T69: 21
B70: 352.43025 | C70: 3.8640042 | D70: 4.8918976 | E70: 0.32970353 | F70: -1.0298042 | G70: 0.0029153145 | H70: 22 | I70: -1.0292638 | J70: -1.0258457 | K70: -1.028452 | L70: -1.0346775 | M70: -1.030782 | N70: 20240511_174018 | O70: n_estimators | P70: 150 | Q70: min_samples_split | R70: 10 | S70: max_depth | T70: 100
B71: 240.16753 | C71: 3.4608575 | D71: 3.1960032 | E71: 0.14070186 | F71: -1.0308078 | G71: 0.0029980155 | H71: 23 | I71: -1.030254 | J71: -1.0266095 | K71: -1.0296385 | L71: -1.0357821 | M71: -1.0317549 | N71: 20240511_174018 | O71: n_estimators | P71: 100 | Q71: min_samples_split | R71: 10 | S71: max_depth | T71: 36
B72: 4.4941197 | C72: 0.21352655 | D72: 0.064830208 | E72: 0.0022935099 | F72: -1.0482212 | G72: 0.0029199074 | H72: 29 | I72: -1.0500113 | J72: -1.0447946 | K72: -1.0448111 | L72: -1.052033 | M72: -1.049456 | N72: 20240511_174018 | O72: n_estimators | P72: 10 | Q72: min_samples_split | R72: 2 | S72: max_depth | T72: 5
B73: 31.329938 | C73: 1.4528009 | D73: 0.41086416 | E73: 0.051333904 | F73: -1.082787 | G73: 0.0025874113 | H73: 34 | I73: -1.085074 | J73: -1.0800841 | K73: -1.0807032 | L73: -1.0866321 | M73: -1.0814415 | N73: 20240511_174018 | O73: n_estimators | P73: 100 | Q73: min_samples_split | R73: 100 | S73: max_depth | T73: 3
B74: 13.39048 | C74: 0.50483407 | D74: 0.18839335 | E74: 0.015377181 | F74: -1.0151973 | G74: 0.0032904551 | H74: 11 | I74: -1.0153747 | J74: -1.0098937 | K74: -1.0140799 | L74: -1.019937 | M74: -1.0167013 | N74: 20240511_174018 | O74: n_estimators | P74: 10 | Q74: min_samples_split | R74: 100 | S74: max_depth | T74: 21
B75: 4.6516295 | C75: 0.082153272 | D75: 0.062003565 | E75: 0.0041205185 | F75: -1.0482212 | G75: 0.0029199074 | H75: 29 | I75: -1.0500113 | J75: -1.0447946 | K75: -1.0448111 | L75: -1.052033 | M75: -1.049456 | N75: 20240511_174018 | O75: n_estimators | P75: 10 | Q75: min_samples_split | R75: 10 | S75: max_depth | T75: 5
B76: 392.25902 | C76: 1.8735699 | D76: 4.9498047 | E76: 0.22392765 | F76: -1.0290591 | G76: 0.00300803 | H76: 17 | I76: -1.0301441 | J76: -1.0248186 | K76: -1.0266524 | L76: -1.0333928 | M76: -1.0302876 | N76: 20240511_174018 | O76: n_estimators | P76: 500 | Q76: min_samples_split | R76: 100 | S76: max_depth | T76: 8
B77: 141.74238 | C77: 1.7462804 | D77: 2.0590613 | E77: 0.16130279 | F77: -1.0096846 | G77: 0.0032023355 | H77: 5 | I77: -1.0098917 | J77: -1.0045655 | K77: -1.0084673 | L77: -1.014292 | M77: -1.0112067 | N77: 20240511_174018 | O77: n_estimators | P77: 100 | Q77: min_samples_split | R77: 100 | S77: max_depth | T77: 36
B78: 48.618827 | C78: 2.3233566 | D78: 0.66431136 | E78: 0.027952519 | F78: -1.082914 | G78: 0.0026038265 | H78: 39 | I78: -1.0854831 | J78: -1.0801568 | K78: -1.0808007 | L78: -1.086573 | M78: -1.0815565 | N78: 20240511_174018 | O78: n_estimators | P78: 150 | Q78: min_samples_split | R78: 100 | S78: max_depth | T78: 3
... B106: 668.51764 | C106: 48.891759 | D106: 8.1124505 | E106: 1.5711414 | F106: -1.0288176 | G106: 0.0029295414 | H106: 16 | I106: -1.0281596 | J106: -1.0247121 | K106: -1.0275617 | L106: -1.0335491 | M106: -1.0301055 | N106: 20240511_174018 | O106: n_estimators | P106: 300 | Q106: min_samples_split | R106: 10 | S106: max_depth | T106: 100
B107: 14.82322 | C107: 0.19058457 | D107: 1.6561551 | E107: 0.018610641 | F107: -1.0313967 | G107: 0.0034495675 | H107: 51 | I107: -1.0326361 | J107: -1.0254422 | K107: -1.0302639 | L107: -1.0357564 | M107: -1.0328849 | N107: 20240512_070043 | O107: subsample | P107: 0.8 | Q107: reg_lambda | R107: 0.1 | S107: reg_alpha | T107: 0.001 | U107: n_estimators | V107: 300 | W107: max_depth | X107: 13 | Y107: learning_rate | Z107: 0.1 | AA107: gamma | AB107: 0.7 | AC107: colsample_bytree | AD107: 1
B108: 26.934199 | C108: 1.5135255 | D108: 0.12736969 | E108: 0.014993966 | F108: -1.2586168 | G108: 0.0030059476 | H108: 94 | I108: -1.2619491 | J108: -1.2536213 | K108: -1.2608984 | L108: -1.2569432 | M108: -1.259672 | N108: 20240512_070043 | O108: subsample | P108: 1 | Q108: reg_lambda | R108: 0 | S108: reg_alpha | T108: 0.005 | U108: n_estimators | V108: 100 | W108: max_depth | X108: 21 | Y108: learning_rate | Z108: 0.8 | AA108: gamma | AB108: 0.5 | AC108: colsample_bytree | AD108: 1
B109: 13.367655 | C109: 2.1807565 | D109: 0.43275051 | E109: 0.14091727 | F109: -0.99976482 | G109: 0.0029714312 | H109: 2 | I109: -1.0008755 | J109: -0.99496229 | K109: -0.99813995 | L109: -1.0036632 | M109: -1.0011831 | N109: 20240512_070043 | O109: subsample | P109: 0.6 | Q109: reg_lambda | R109: 0.1 | S109: reg_alpha | T109: 1 | U109: n_estimators | V109: 400 | W109: max_depth | X109: 3 | Y109: learning_rate | Z109: 0.2 | AA109: gamma | AB109: 0.4 | AC109: colsample_bytree | AD109: 0.9
B110: 62.740615 | C110: 0.90987457 | D110: 3.0782172 | E110: 0.075901098 | F110: -1.0658617 | G110: 0.0040935352 | H110: 68 | I110: -1.0651693 | J110: -1.059254 | K110: -1.0655519 | L110: -1.0719681 | M110: -1.0673649 | N110: 20240512_070043 | O110: subsample | P110: 1 | Q110: reg_lambda | R110: 0.001 | S110: reg_alpha | T110: 0.05 | U110: n_estimators | V110: 400 | W110: max_depth | X110: 21 | Y110: learning_rate | Z110: 0.1 | AA110: gamma | AB110: 0.2 | AC110: colsample_bytree | AD110: 0.8
B111: 16.926011 | C111: 0.72175512 | D111: 0.45979381 | E111: 0.016916884 | F111: -1.0057899 | G111: 0.0031138028 | H111: 24 | I111: -1.0063172 | J111: -1.0009977 | K111: -1.0039262 | L111: -1.0100753 | M111: -1.0076333 | N111: 20240512_070043 | O111: subsample | P111: 0.8 | Q111: reg_lambda | R111: 1 | S111: reg_alpha | T111: 0.05 | U111: n_estimators | V111: 400 | W111: max_depth | X111: 3 | Y111: learning_rate | Z111: 0.1 | AA111: gamma | AB111: 0.7 | AC111: colsample_bytree | AD111: 0.6
B112: 42.141556 | C112: 0.63606875 | D112: 6.8246859 | E112: 0.29035602 | F112: -1.0174504 | G112: 0.0028714382 | H112: 37 | I112: -1.0185964 | J112: -1.0131757 | K112: -1.015473 | L112: -1.0215352 | M112: -1.018472 | N112: 20240512_070043 | O112: subsample | P112: 0.6 | Q112: reg_lambda | R112: 0.005 | S112: reg_alpha | T112: 0.005 | U112: n_estimators | V112: 300 | W112: max_depth | X112: 13 | Y112: learning_rate | Z112: 0.01 | AA112: gamma | AB112: 1 | AC112: colsample_bytree | AD112: 0.6
B113: 9.9978261 | C113: 0.6928412 | D113: 0.35943747 | E113: 0.093048628 | F113: -1.0021507 | G113: 0.0031289961 | H113: 17 | I113: -1.0031334 | J113: -0.99718908 | K113: -1.0002448 | L113: -1.0061933 | M113: -1.0039931 | N113: 20240512_070043 | O113: subsample | P113: 0.8 | Q113: reg_lambda | R113: 0.5 | S113: reg_alpha | T113: 0.001 | U113: n_estimators | V113: 200 | W113: max_depth | X113: 3 | Y113: learning_rate | Z113: 0.5 | AA113: gamma | AB113: 0.1 | AC113: colsample_bytree | AD113: 0.7
B114: 40.79965 | C114: 1.3084633 | D114: 3.4309411 | E114: 0.14389114 | F114: -1.0414176 | G114: 0.003366484 | H114: 59 | I114: -1.0412645 | J114: -1.0367544 | K114: -1.0392132 | L114: -1.04657 | M114: -1.0432858 | N114: 20240512_070043 | O114: subsample | P114: 0.7 | Q114: reg_lambda | R114: 0.005 | S114: reg_alpha | T114: 0.1 | U114: n_estimators | V114: 300 | W114: max_depth | X114: 21 | Y114: learning_rate | Z114: 0.1 | AA114: gamma | AB114: 0.7 | AC114: colsample_bytree | AD114: 0.6
B115: 41.100468 | C115: 0.71984323 | D115: 6.1643981 | E115: 0.2594371 | F115: -1.0153908 | G115: 0.0028373259 | H115: 36 | I115: -1.0161106 | J115: -1.0110196 | K115: -1.0138376 | L115: -1.0195212 | M115: -1.0164652 | N115: 20240512_070043 | O115: subsample | P115: 0.6 | Q115: reg_lambda | R115: 0 | S115: reg_alpha | T115: 0.001 | U115: n_estimators | V115: 200 | W115: max_depth | X115: 13 | Y115: learning_rate | Z115: 0.01 | AA115: gamma | AB115: 0.8 | AC115: colsample_bytree | AD115: 0.9
B116: 356.52013 | C116: 7.9672699 | D116: 28.258307 | E116: 5.2662118 | F116: -1.1813165 | G116: 0.0041981863 | H116: 87 | I116: -1.1791223 | J116: -1.1742365 | K116: -1.183367 | L116: -1.1861299 | M116: -1.1837269 | N116: 20240512_070043 | O116: subsample | P116: 0.8 | Q116: reg_lambda | R116: 0.5 | S116: reg_alpha | T116: 0.005 | U116: n_estimators | V116: 400 | W116: max_depth | X116: 21 | Y116: learning_rate | Z116: 0.2 | AA116: gamma | AB116: 0 | AC116: colsample_bytree | AD116: 0.8
B117: 33.064513 | C117: 1.1331549 | D117: 2.552081 | E117: 0.095482003 | F117: -1.0077115 | G117: 0.0028661217 | H117: 28 | I117: -1.0087038 | J117: -1.0031757 | K117: -1.0060747 | L117: -1.011609 | M117: -1.0089943 | N117: 20240512_070043 | O117: subsample | P117: 0.9 | Q117: reg_lambda | R117: 0.005 | S117: reg_alpha | T117: 0.05 | U117: n_estimators | V117: 400 | W117: max_depth | X117: 8 | Y117: learning_rate | Z117: 0.01 | AA117: gamma | AB117: 0.7 | AC117: colsample_bytree | AD117: 0.8
B118: 24.059703 | C118: 0.91621204 | D118: 3.2860689 | E118: 0.16266121 | F118: -1.039834 | G118: 0.0029256997 | H118: 57 | I118: -1.038602 | J118: -1.0362798 | K118: -1.0381662 | L118: -1.0446484 | M118: -1.0414737 | N118: 20240512_070043 | O118: subsample | P118: 0.7 | Q118: reg_lambda | R118: 0.05 | S118: reg_alpha | T118: 0 | U118: n_estimators | V118: 200 | W118: max_depth | X118: 13 | Y118: learning_rate | Z118: 0.1 | AA118: gamma | AB118: 0.6 | AC118: colsample_bytree | AD118: 0.9
... B206: 54.105831 | C206: 0.63461906 | D206: 2.4310789 | E206: 0.33351002 | F206: -1.1168829 | G206: 0.0047371069 | H206: 80 | I206: -1.1127747 | J206: -1.1115634 | K206: -1.1169389 | L206: -1.1249679 | M206: -1.1181698 | N206: 20240512_070043 | O206: subsample | P206: 0.6 | Q206: reg_lambda | R206: 0.1 | S206: reg_alpha | T206: 0.005 | U206: n_estimators | V206: 100 | W206: max_depth | X206: 21 | Y206: learning_rate | Z206: 0.2 | AA206: gamma | AB206: 0.4 | AC206: colsample_bytree | AD206: 0.8
B207: 0.1626286 | C207: 0.0077454677 | D207: 0.0063406944 | E207: 0.0077670597 | F207: -1.2088904 | G207: 0.0036520767 | H207: 6 | I207: -1.2126441 | J207: -1.209008 | K207: -1.2042656 | L207: -1.2131986 | M207: -1.2053359 | N207: 20240519_212952 | O207: max_iter | P207: 10000 | Q207: l1_ratio | R207: 0.7 | S207: alpha | T207: 0.4
B208: 0.10297451 | C208: 0.01488299 | D208: 0.012047625 | E208: 0.0087238826 | F208: -1.2407202 | G208: 0.0038419033 | H208: 9 | I208: -1.2445136 | J208: -1.24081 | K208: -1.2363734 | L208: -1.2454466 | M208: -1.2364576 | N208: 20240519_212952 | O208: max_iter | P208: 10000 | Q208: l1_ratio | R208: 0.4 | S208: alpha | T208: 10
B209: 0.098104048 | C209: 0.0080269307 | D209: 0.0061265945 | E209: 0.0058518343 | F209: -1.2407202 | G209: 0.0038419033 | H209: 9 | I209: -1.2445136 | J209: -1.24081 | K209: -1.2363734 | L209: -1.2454466 | M209: -1.2364576 | N209: 20240519_212952 | O209: max_iter | P209: 10000 | Q209: l1_ratio | R209: 0.6 | S209: alpha | T209: 3
B210: 158.37676 | C210: 0.96271399 | D210: 0.012497187 | E210: 0.011690462 | F210: -1.1242264 | G210: 0.0054273458 | H210: 1 | I210: -1.1256806 | J210: -1.1175315 | K210: -1.121457 | L210: -1.1337357 | M210: -1.122727 | N210: 20240519_212952 | O210: max_iter | P210: 10000 | Q210: l1_ratio | R210: 0.4 | S210: alpha | T210: 0
B211: 0.12347651 | C211: 0.010909975 | D211: 0.0062499523 | E211: 0.0076545971 | F211: -1.2407202 | G211: 0.0038419033 | H211: 9 | I211: -1.2445136 | J211: -1.24081 | K211: -1.2363734 | L211: -1.2454466 | M211: -1.2364576 | N211: 20240519_212952 | O211: max_iter | P211: 10000 | Q211: l1_ratio | R211: 0.9 | S211: alpha | T211: 7
B212: 0.1374229 | C212: 0.0062183792 | D212: 0.0093739986 | E212: 0.0076538381 | F212: -1.2407202 | G212: 0.0038419033 | H212: 9 | I212: -1.2445136 | J212: -1.24081 | K212: -1.2363734 | L212: -1.2454466 | M212: -1.2364576 | N212: 20240519_212952 | O212: max_iter | P212: 10000 | Q212: l1_ratio | R212: 0.7 | S212: alpha | T212: 100
B213: 0.12162967 | C213: 0.01194255 | D213: 0.015623283 | E213: 1.3520667e-06 | F213: -1.2407202 | G213: 0.0038419033 | H213: 9 | I213: -1.2445136 | J213: -1.24081 | K213: -1.2363734 | L213: -1.2454466 | M213: -1.2364576 | N213: 20240519_212952 | O213: max_iter | P213: 10000 | Q213: l1_ratio | R213: 1 | S213: alpha | T213: 1
B214: 0.22842879 | C214: 0.015965324 | D214: 0.00937953 | E214: 0.0076583574 | F214: -1.1869071 | G214: 0.0033811385 | H214: 4 | I214: -1.1899963 | J214: -1.186324 | K214: -1.1819767 | L214: -1.1912839 | M214: -1.1849547 | N214: 20240519_212952 | O214: max_iter | P214: 10000 | Q214: l1_ratio | R214: 0.1 | S214: alpha | T214: 1
B215: 157.25039 | C215: 3.6543148 | D215: 0.021876717 | E215: 0.0076504336 | F215: -1.2378429 | G215: 0.0038168188 | H215: 8 | I215: -1.2416234 | J215: -1.2379162 | K215: -1.2334675 | L215: -1.2425344 | M215: -1.233673 | N215: 20240519_212952 | O215: max_iter | P215: 10000 | Q215: l1_ratio | R215: 0 | S215: alpha | T215: 100
B216: 0.16263065 | C216: 0.0078365796 | D216: 0.01562376 | E216: 0.0098812887 | F216: -1.2407202 | G216: 0.0038419033 | H216: 9 | I216: -1.2445136 | J216: -1.24081 | K216: -1.2363734 | L216: -1.2454466 | M216: -1.2364576 | N216: 20240519_212952 | O216: max_iter | P216: 10000 | Q216: l1_ratio | R216: 0.3 | S216: alpha | T216: 10
B217: 0.34758487 | C217: 0.011559935 | D217: 0.00625453 | E217: 0.0076602046 | F217: -1.1607875 | G217: 0.0038384522 | H217: 2 | I217: -1.1628157 | J217: -1.1584063 | K217: -1.1556886 | L217: -1.1669064 | M217: -1.1601206 | N217: 20240519_212952 | O217: max_iter | P217: 10000 | Q217: l1_ratio | R217: 0.1 | S217: alpha | T217: 0.4
B218: 0.16582899 | C218: 0.01267368 | D218: 0.012504482 | E218: 0.006252246 | F218: -1.2407202 | G218: 0.0038419033 | H218: 9 | I218: -1.2445136 | J218: -1.24081 | K218: -1.2363734 | L218: -1.2454466 | M218: -1.2364576 | N218: 20240519_212952 | O218: max_iter | P218: 10000 | Q218: l1_ratio | R218: 0.3 | S218: alpha | T218: 100
... B226: 0.21866899 | C226: 0.046192288 | D226: 0.012501144 | E226: 0.011691712 | F226: -1.2407202 | G226: 0.0038419033 | H226: 9 | I226: -1.2445136 | J226: -1.24081 | K226: -1.2363734 | L226: -1.2454466 | M226: -1.2364576 | N226: 20240519_212952 | O226: max_iter | P226: 10000 | Q226: l1_ratio | R226: 0.3 | S226: alpha | T226: 2
B227: 1.8053331 | C227: 0.26075494 | D227: 0.030822897 | E227: 0.012461125 | F227: -1.0558342 | G227: 0.0038179384 | H227: 7 | I227: -1.0538868 | J227: -1.0512073 | K227: -1.0537527 | L227: -1.0618779 | M227: -1.0584463 | N227: 20240519_214228 | O227: min_samples_split | P227: 100 | Q227: max_depth | R227: 36 | S227: criterion | T227: friedman_mse
B228: 11130.76 | C228: 323.90476 | D228: 0.026587343 | E228: 0.0035268241 | F228: -1.1247426 | G228: 0.0013853988 | H228: 24 | I228: -1.1237433 | J228: -1.1238174 | K228: -1.1271364 | L228: -1.1235327 | M228: -1.125483 | N228: 20240519_214228 | O228: min_samples_split | P228: 2 | Q228: max_depth | R228: 21 | S228: criterion | T228: absolute_error
B229: 8194.4334 | C229: 78.435775 | D229: 0.016299868 | E229: 0.0028342773 | F229: -1.1159732 | G229: 0.0031667753 | H229: 23 | I229: -1.1165849 | J229: -1.1149611 | K229: -1.1104265 | L229: -1.1185629 | M229: -1.1193305 | N229: 20240519_214228 | O229: min_samples_split | P229: 5 | Q229: max_depth | R229: 13 | S229: criterion | T229: absolute_error
B230: 0.87744455 | C230: 0.093498244 | D230: 0.015401316 | E230: 0.0036910218 | F230: -1.0555474 | G230: 0.0031498954 | H230: 6 | I230: -1.056285 | J230: -1.0515388 | K230: -1.0522247 | L230: -1.0591744 | M230: -1.058514 | N230: 20240519_214228 | O230: min_samples_split | P230: 100 | Q230: max_depth | R230: 5 | S230: criterion | T230: friedman_mse
B231: 1.9476369 | C231: 0.056931378 | D231: 0.023741245 | E231: 0.0026247145 | F231: -1.0621412 | G231: 0.0026605521 | H231: 11 | I231: -1.0635071 | J231: -1.0587333 | K231: -1.0595007 | L231: -1.0658928 | M231: -1.0630722 | N231: 20240519_214228 | O231: min_samples_split | P231: 10 | Q231: max_depth | R231: 13 | S231: criterion | T231: friedman_mse
B232: 15106.243 | C232: 862.26483 | D232: 0.067712021 | E232: 0.0064084291 | F232: -1.2339299 | G232: 0.0033173988 | H232: 31 | I232: -1.2301531 | J232: -1.2327381 | K232: -1.238092 | L232: -1.2376265 | M232: -1.2310397 | N232: 20240519_214228 | O232: min_samples_split | P232: 25 | Q232: max_depth | R232: 100 | S232: criterion | T232: absolute_error
B233: 0.61503296 | C233: 0.030530985 | D233: 0.012448978 | E233: 0.0023702073 | F233: -1.0922802 | G233: 0.0029442418 | H233: 14 | I233: -1.095375 | J233: -1.0878675 | K233: -1.0898977 | L233: -1.095071 | M233: -1.09319 | N233: 20240519_214228 | O233: min_samples_split | P233: 100 | Q233: max_depth | R233: 3 | S233: criterion | T233: squared_error
B234: 3.1904053 | C234: 0.10617344 | D234: 0.030051613 | E234: 0.0042374939 | F234: -1.0662663 | G234: 0.0021547758 | H234: 13 | I234: -1.0650323 | J234: -1.0630472 | K234: -1.0660986 | L234: -1.0691366 | M234: -1.0680166 | N234: 20240519_214228 | O234: min_samples_split | P234: 2 | Q234: max_depth | R234: 13 | S234: criterion | T234: poisson
B235: 0.70639639 | C235: 0.097735866 | D235: 0.014182663 | E235: 0.0031561476 | F235: -1.0922802 | G235: 0.0029442418 | H235: 14 | I235: -1.095375 | J235: -1.0878675 | K235: -1.0898977 | L235: -1.095071 | M235: -1.09319 | N235: 20240519_214228 | O235: min_samples_split | P235: 25 | Q235: max_depth | R235: 3 | S235: criterion | T235: squared_error
B236: 5.4322296 | C236: 0.24056073 | D236: 0.079754925 | E236: 0.0063805193 | F236: -1.3683397 | G236: 0.0037430448 | H236: 36 | I236: -1.3646931 | J236: -1.3709844 | K236: -1.3638565 | L236: -1.3683789 | M236: -1.3737857 | N236: 20240519_214228 | O236: min_samples_split | P236: 5 | Q236: max_depth | R236: 36 | S236: criterion | T236: squared_error
B237: 6.284927 | C237: 0.26147929 | D237: 0.08562398 | E237: 0.0071788539 | F237: -1.4437615 | G237: 0.0037777722 | H237: 38 | I237: -1.4402426 | J237: -1.4446948 | K237: -1.4393403 | L237: -1.4446186 | M237: -1.4499115 | N237: 20240519_214228 | O237: min_samples_split | P237: 2 | Q237: max_depth | R237: 57 | S237: criterion | T237: squared_error
B238: 14859.942 | C238: 1825.0716 | D238: 0.10774059 | E238: 0.01736207 | F238: -1.3792552 | G238: 0.0067690936 | H238: 37 | I238: -1.3696623 | J238: -1.3727157 | K238: -1.3832346 | L238: -1.3838094 | M238: -1.3868538 | N238: 20240519_214228 | O238: min_samples_split | P238: 5 | Q238: max_depth | R238: 100 | S238: criterion | T238: absolute_error
... B266: 2.3812184 | C266: 0.16540374 | D266: 0.032253981 | E266: 0.00486053 | F266: -1.0558342 | G266: 0.0038179384 | H266: 7 | I266: -1.0538868 | J266: -1.0512073 | K266: -1.0537527 | L266: -1.0618779 | M266: -1.0584463 | N266: 20240519_214228 | O266: min_samples_split | P266: 100 | Q266: max_depth | R266: 57 | S266: criterion | T266: squared_error
B267: 0.17806988 | C267: 0.0073370036 | D267: 0.0078184128 | E267: 0.0031989819 | F267: -1.2106729 | G267: 0.0039779712 | H267: 3 | I267: -1.2145585 | J267: -1.2108222 | K267: -1.2061537 | L267: -1.2155767 | M267: -1.2062535 | N267: 20240525_195654 | O267: max_iter | P267: 100000 | Q267: l1_ratio | R267: 0.8 | S267: alpha | T267: 0.4
B268: 0.16915092 | C268: 0.011404313 | D268: 0.0094704628 | E268: 0.0018172005 | F268: -1.2403367 | G268: 0.0038439171 | H268: 4 | I268: -1.2441621 | J268: -1.2406536 | K268: -1.2360862 | L268: -1.2449226 | M268: -1.2358593 | N268: 20240525_195654 | O268: max_iter | P268: 100000 | Q268: l1_ratio | R268: 0.5 | S268: alpha | T268: 0.8
B269: 0.18521495 | C269: 0.021368973 | D269: 0.008331728 | E269: 0.0035707255 | F269: -1.2407202 | G269: 0.0038419033 | H269: 6 | I269: -1.2445136 | J269: -1.24081 | K269: -1.2363734 | L269: -1.2454466 | M269: -1.2364576 | N269: 20240525_195654 | O269: max_iter | P269: 100000 | Q269: l1_ratio | R269: 1 | S269: alpha | T269: 10000
B270: 0.18328452 | C270: 0.017873115 | D270: 0.0087180614 | E270: 0.0035126191 | F270: -1.2407202 | G270: 0.0038419033 | H270: 6 | I270: -1.2445136 | J270: -1.24081 | K270: -1.2363734 | L270: -1.2454466 | M270: -1.2364576 | N270: 20240525_195654 | O270: max_iter | P270: 100000 | Q270: l1_ratio | R270: 0.8 | S270: alpha | T270: 100
B271: 0.20296183 | C271: 0.022686119 | D271: 0.010083151 | E271: 0.0039416095 | F271: -1.2407202 | G271: 0.0038419033 | H271: 6 | I271: -1.2445136 | J271: -1.24081 | K271: -1.2363734 | L271: -1.2454466 | M271: -1.2364576 | N271: 20240525_195654 | O271: max_iter | P271: 100000 | Q271: l1_ratio | R271: 0.3 | S271: alpha | T271: 10
B272: 0.21626344 | C272: 0.012337808 | D272: 0.0092033386 | E272: 0.0021724928 | F272: -1.1564664 | G272: 0.0033794233 | H272: 2 | I272: -1.1600321 | J272: -1.1550498 | K272: -1.1523405 | L272: -1.1608757 | M272: -1.1540339 | N272: 20240525_195654 | O272: max_iter | P272: 100000 | Q272: l1_ratio | R272: 0.3 | S272: alpha | T272: 0.4
B273: 2459.405 | C273: 2.4108719 | D273: 0.015350246 | E273: 0.0069646625 | F273: -1.1273544 | G273: 0.003868588 | H273: 1 | I273: -1.1315432 | J273: -1.1235095 | K273: -1.1229256 | L273: -1.1320934 | M273: -1.1267002 | N273: 20240525_195654 | O273: max_iter | P273: 100000 | Q273: l1_ratio | R273: 0.1 | S273: alpha | T273: 0
B274: 0.2161232 | C274: 0.019837852 | D274: 0.0090648651 | E274: 0.00038305197 | F274: -1.2403782 | G274: 0.0038365265 | H274: 5 | I274: -1.2441948 | J274: -1.2406682 | K274: -1.2361129 | L274: -1.2449708 | M274: -1.2359442 | N274: 20240525_195654 | O274: max_iter | P274: 100000 | Q274: l1_ratio | R274: 0.2 | S274: alpha | T274: 2
B275: 0.23906951 | C275: 0.029960675 | D275: 0.0089021206 | E275: 0.004124348 | F275: -1.2407202 | G275: 0.0038419033 | H275: 6 | I275: -1.2445136 | J275: -1.24081 | K275: -1.2363734 | L275: -1.2454466 | M275: -1.2364576 | N275: 20240525_195654 | O275: max_iter | P275: 100000 | Q275: l1_ratio | R275: 1 | S275: alpha | T275: 7
B276: 0.29348388 | C276: 0.0098720319 | D276: 0.017973423 | E276: 0.015792222 | F276: -1.2407202 | G276: 0.0038419033 | H276: 6 | I276: -1.2445136 | J276: -1.24081 | K276: -1.2363734 | L276: -1.2454466 | M276: -1.2364576 | N276: 20240525_195654 | O276: max_iter | P276: 100000 | Q276: l1_ratio | R276: 0.6 | S276: alpha | T276: 0.8
B277: 0.79916415 | C277: 0.054018038 | D277: 0.012679148 | E277: 0.0031150695 | F277: -1.1182865 | G277: 0.003280466 | H277: 3 | I277: -1.1214788 | J277: -1.1173695 | K277: -1.1145965 | L277: -1.1227461 | M277: -1.1152416 | N277: 20240525_214508 | O277: max_iter | P277: 100000 | Q277: l1_ratio | R277: 0.8 | S277: alpha | T277: 0.4
B278: 0.7021349 | C278: 0.095101186 | D278: 0.016978455 | E278: 0.0042162598 | F278: -1.159622 | G278: 0.0036756288 | H278: 4 | I278: -1.163551 | J278: -1.1590179 | K278: -1.1561344 | L278: -1.1641516 | M278: -1.1552552 | N278: 20240525_214508 | O278: max_iter | P278: 100000 | Q278: l1_ratio | R278: 0.5 | S278: alpha | T278: 0.8
... B296: 1.2759436 | C296: 0.14499292 | D296: 0.029124689 | E296: 0.0038663409 | F296: -1.1843438 | G296: 0.0040554183 | H296: 6 | I296: -1.1887 | J296: -1.1833797 | K296: -1.1802426 | L296: -1.1894552 | M296: -1.1799415 | N296: 20240526_062912 | O296: max_iter | P296: 100000 | Q296: l1_ratio | R296: 0.6 | S296: alpha | T296: 0.8
B297: 2.4695081 | C297: 0.055290035 | D297: 2678.6057 | E297: 79.699654 | F297: -1.1811452 | G297: 0.0055925618 | H297: 28 | I297: -1.1901423 | J297: -1.1743916 | K297: -1.1761041 | L297: -1.1830434 | M297: -1.1820444 | N297: 20240526_190924 | O297: weights | P297: distance | Q297: p | R297: 4 | S297: n_neighbors | T297: 7
B298: 2.1418798 | C298: 0.41852628 | D298: 2510.1948 | E298: 76.666415 | F298: -1.1829779 | G298: 0.0053753713 | H298: 30 | I298: -1.1915737 | J298: -1.1766696 | K298: -1.1779315 | L298: -1.1852291 | M298: -1.1834856 | N298: 20240526_190924 | O298: weights | P298: distance | Q298: p | R298: 5 | S298: n_neighbors | T298: 7
B299: 1.7741016 | C299: 0.12782318 | D299: 1090.7693 | E299: 26.28569 | F299: -1.1248265 | G299: 0.0041861249 | H299: 5 | I299: -1.1301268 | J299: -1.1220482 | K299: -1.1195899 | L299: -1.1294009 | M299: -1.1229664 | N299: 20240526_190924 | O299: weights | P299: distance | Q299: p | R299: 2 | S299: n_neighbors | T299: 100
B300: 1.8247051 | C300: 0.12652174 | D300: 1541.0532 | E300: 28.306693 | F300: -1.1242563 | G300: 0.0045218676 | H300: 3 | I300: -1.1306298 | J300: -1.1209783 | K300: -1.1194445 | L300: -1.1287368 | M300: -1.1214918 | N300: 20240526_190924 | O300: weights | P300: distance | Q300: p | R300: 1 | S300: n_neighbors | T300: 30
B301: 1.8855792 | C301: 0.099411619 | D301: 2988.3679 | E301: 94.519704 | F301: -1.1796346 | G301: 0.0054238269 | H301: 27 | I301: -1.1884167 | J301: -1.1732339 | K301: -1.17493 | L301: -1.1822388 | M301: -1.1793537 | N301: 20240526_190924 | O301: weights | P301: distance | Q301: p | R301: 3 | S301: n_neighbors | T301: 7
B302: 1.7967242 | C302: 0.16439093 | D302: 2596.1206 | E302: 106.07339 | F302: -1.168732 | G302: 0.0050675275 | H302: 25 | I302: -1.1758071 | J302: -1.1619938 | K302: -1.1643268 | L302: -1.1723873 | M302: -1.1691452 | N302: 20240526_190924 | O302: weights | P302: uniform | Q302: p | R302: 5 | S302: n_neighbors | T302: 9
...

Sheet Dropdowns
B2: Dropdowns
F6: Train values | J6: Test values | N6: Train bubbles | R6: Test bubbles
B8: Execution name | D8: Variables for index match | F8: =D9 -> Real_20240512_070043 | G8: =D10 -> Predicted_20240512_070043 | H8: Bucket | J8: =F8 -> Real_20240512_070043 | K8: =G8 -> Predicted_20240512_070043 | L8: Bucket | N8: Real | O8: Predicted bucket | P8: Count | R8: =N8 -> Real | S8: =O8 -> Predicted bucket | T8: =P8 -> Count | V8: Hyperparameters | X8: =Dashboard!C65&" - " &Dashboard!C7 -> n_estimators - 20240512_070043 | Y8: mean_test_score
B9: {=_xlfn.UNIQUE('General inputs'!B6:B305)} -> 20260427_181736 | D9: ="Real_"&Dashboard!$C$7 -> Real_20240512_070043 | F9: {=INDEX('Train prediction inputs'!$B$6:$ZZ$304, , MATCH(F$8, 'Train prediction inputs'!$B$5:$ZZ$5, 0))} -> 3 | G9: {=INDEX('Train prediction inputs'!$B$6:$ZZ$304, , MATCH(G$8, 'Train prediction inputs'!$B$5:$ZZ$5, 0))} -> 3.3647306 | H9: =IF(G9<0.5, 0, IF(G9<1.5, 1, IF(G9<2.5, 2, IF(G9<3.5, 3, IF(G9<4.5, 4, 5))))) -> 3 | J9: {=INDEX('Test prediction inputs'!$B$6:$ZZ$304, , MATCH(F$8, 'Test prediction inputs'!$B$5:$ZZ$5, 0))} -> 4 | K9: {=INDEX('Test prediction inputs'!$B$6:$ZZ$304, , MATCH(G$8, 'Test prediction inputs'!$B$5:$ZZ$5, 0))} -> 3.891651 | L9: =IF(K9<0.5, 0, IF(K9<1.5, 1, IF(K9<2.5, 2, IF(K9<3.5, 3, IF(K9<4.5, 4, 5))))) -> 4 | N9: 1 | O9: 1 | P9: =COUNTIFS(_xlfn.ANCHORARRAY($F$9), N9, $H$9:$H$307, O9) -> 3 | R9: =N9 -> 1 | S9: =O9 -> 1 | T9: =COUNTIFS(_xlfn.ANCHORARRAY($J$9), R9, $L$9:$L$307, S9) -> 2 | V9: =INDEX('Execution deepdive inputs'!$O$7:$O$1048576, MATCH(Dashboard!$C$7, 'Execution deepdive inputs'!$N$7:$N$1048576, 0)) -> subsample | X9: {=_xlfn._xlws.FILTER(INDEX('Execution deepdive inputs'!$B$7:$AA$25000, , MATCH(Dashboard!$C$65, 'Execution deepdive inputs'!B5:AA5, 0)+1), 'Execution deepdive inputs'!$N$7:$N$25000=Dashboard!$C$7)} -> 300 | Y9: {=_xlfn._xlws.FILTER('Execution deepdive inputs'!$F$7:$F$25000, 'Execution deepdive inputs'!$N$7:$N$25000=Dashboard!$C$7)} -> -1.0313967 | AD9: =COUNTIFS(Dropdowns!$F$9#, Dashboard!$C25, Dropdowns!$H$9:$H$307, Dashboard!D$24) / COUNTA(Dropdowns!$F$9#)
B10: 20260427_181817 | D10: ="Predicted_"&Dashboard!$C$7 -> Predicted_20240512_070043 | F10: 5 | G10: 4.3741765 | H10: =IF(G10<0.5, 0, IF(G10<1.5, 1, IF(G10<2.5, 2, IF(G10<3.5, 3, IF(G10<4.5, 4, 5))))) -> 4 | J10: 3 | K10: 3.5741134 | L10: =IF(K10<0.5, 0, IF(K10<1.5, 1, IF(K10<2.5, 2, IF(K10<3.5, 3, IF(K10<4.5, 4, 5))))) -> 4 | N10: 1 | O10: 2 | P10: =COUNTIFS(_xlfn.ANCHORARRAY($F$9), N10, $H$9:$H$307, O10) -> 9 | R10: =N10 -> 1 | S10: =O10 -> 2 | T10: =COUNTIFS(_xlfn.ANCHORARRAY($J$9), R10, $L$9:$L$307, S10) -> 11 | V10: =INDEX('Execution deepdive inputs'!$Q$7:$Q$1048576, MATCH(Dashboard!$C$7, 'Execution deepdive inputs'!$N$7:$N$1048576, 0)) -> reg_lambda | X10: 100 | Y10: -1.2586168
B11: 20260427_181844 | F11: 3 | G11: 2.808288 | H11: =IF(G11<0.5, 0, IF(G11<1.5, 1, IF(G11<2.5, 2, IF(G11<3.5, 3, IF(G11<4.5, 4, 5))))) -> 3 | J11: 3 | K11: 3.0231738 | L11: =IF(K11<0.5, 0, IF(K11<1.5, 1, IF(K11<2.5, 2, IF(K11<3.5, 3, IF(K11<4.5, 4, 5))))) -> 3 | N11: 1 | O11: 3 | P11: =COUNTIFS(_xlfn.ANCHORARRAY($F$9), N11, $H$9:$H$307, O11) -> 6 | R11: =N11 -> 1 | S11: =O11 -> 3 | T11: =COUNTIFS(_xlfn.ANCHORARRAY($J$9), R11, $L$9:$L$307, S11) -> 6 | V11: =INDEX('Execution deepdive inputs'!$S$7:$S$1048576, MATCH(Dashboard!$C$7, 'Execution deepdive inputs'!$N$7:$N$1048576, 0)) -> reg_alpha | X11: 400 | Y11: -0.99976482
B12: 20260427_181932 | F12: 3 | G12: 4.2254453 | H12: =IF(G12<0.5, 0, IF(G12<1.5, 1, IF(G12<2.5, 2, IF(G12<3.5, 3, IF(G12<4.5, 4, 5))))) -> 4 | J12: 2 | K12: 2.3481338 | L12: =IF(K12<0.5, 0, IF(K12<1.5, 1, IF(K12<2.5, 2, IF(K12<3.5, 3, IF(K12<4.5, 4, 5))))) -> 2 | N12: 1 | O12: 4 | P12: =COUNTIFS(_xlfn.ANCHORARRAY($F$9), N12, $H$9:$H$307, O12) -> 6 | R12: =N12 -> 1 | S12: =O12 -> 4 | T12: =COUNTIFS(_xlfn.ANCHORARRAY($J$9), R12, $L$9:$L$307, S12) -> 10 | V12: =INDEX('Execution deepdive inputs'!$U$7:$U$1048576, MATCH(Dashboard!$C$7, 'Execution deepdive inputs'!$N$7:$N$1048576, 0)) -> n_estimators | X12: 400 | Y12: -1.0658617
B13: 20260427_182011 | F13: 4 | G13: 4.0832624 | H13: =IF(G13<0.5, 0, IF(G13<1.5, 1, IF(G13<2.5, 2, IF(G13<3.5, 3, IF(G13<4.5, 4, 5))))) -> 4 | J13: 3 | K13: 3.8366833 | L13: =IF(K13<0.5, 0, IF(K13<1.5, 1, IF(K13<2.5, 2, IF(K13<3.5, 3, IF(K13<4.5, 4, 5))))) -> 4 | N13: 1 | O13: 5 | P13: =COUNTIFS(_xlfn.ANCHORARRAY($F$9), N13, $H$9:$H$307, O13) -> 0 | R13: =N13 -> 1 | S13: =O13 -> 5 | T13: =COUNTIFS(_xlfn.ANCHORARRAY($J$9), R13, $L$9:$L$307, S13) -> 0 | V13: =INDEX('Execution deepdive inputs'!$W$7:$W$1048576, MATCH(Dashboard!$C$7, 'Execution deepdive inputs'!$N$7:$N$1048576, 0)) -> max_depth | X13: 400 | Y13: -1.0057899
B14: 20260427_182729 | F14: 3 | G14: 4.1902246 | H14: =IF(G14<0.5, 0, IF(G14<1.5, 1, IF(G14<2.5, 2, IF(G14<3.5, 3, IF(G14<4.5, 4, 5))))) -> 4 | J14: 2 | K14: 3.008226 | L14: =IF(K14<0.5, 0, IF(K14<1.5, 1, IF(K14<2.5, 2, IF(K14<3.5, 3, IF(K14<4.5, 4, 5))))) -> 3 | N14: =N9+1 -> 2 | O14: =O9 -> 1 | P14: =COUNTIFS(_xlfn.ANCHORARRAY($F$9), N14, $H$9:$H$307, O14) -> 0 | R14: =N14 -> 2 | S14: =O14 -> 1 | T14: =COUNTIFS(_xlfn.ANCHORARRAY($J$9), R14, $L$9:$L$307, S14) -> 1 | V14: =INDEX('Execution deepdive inputs'!$Y$7:$Y$1048576, MATCH(Dashboard!$C$7, 'Execution deepdive inputs'!$N$7:$N$1048576, 0)) -> learning_rate | X14: 300 | Y14: -1.0174504
B15: 20260427_182755 | F15: 2 | G15: 2.1649487 | H15: =IF(G15<0.5, 0, IF(G15<1.5, 1, IF(G15<2.5, 2, IF(G15<3.5, 3, IF(G15<4.5, 4, 5))))) -> 2 | J15: 5 | K15: 3.31209 | L15: =IF(K15<0.5, 0, IF(K15<1.5, 1, IF(K15<2.5, 2, IF(K15<3.5, 3, IF(K15<4.5, 4, 5))))) -> 3 | N15: =N10+1 -> 2 | O15: =O10 -> 2 | P15: =COUNTIFS(_xlfn.ANCHORARRAY($F$9), N15, $H$9:$H$307, O15) -> 9 | R15: =N15 -> 2 | S15: =O15 -> 2 | T15: =COUNTIFS(_xlfn.ANCHORARRAY($J$9), R15, $L$9:$L$307, S15) -> 7 | V15: =INDEX('Execution deepdive inputs'!$AA$7:$AA$1048576, MATCH(Dashboard!$C$7, 'Execution deepdive inputs'!$N$7:$N$1048576, 0)) -> gamma | X15: 200 | Y15: -1.0021507
B16: 20260427_182824 | F16: 5 | G16: 4.359283 | H16: =IF(G16<0.5, 0, IF(G16<1.5, 1, IF(G16<2.5, 2, IF(G16<3.5, 3, IF(G16<4.5, 4, 5))))) -> 4 | J16: 4 | K16: 3.6984987 | L16: =IF(K16<0.5, 0, IF(K16<1.5, 1, IF(K16<2.5, 2, IF(K16<3.5, 3, IF(K16<4.5, 4, 5))))) -> 4 | N16: =N11+1 -> 2 | O16: =O11 -> 3 | P16: =COUNTIFS(_xlfn.ANCHORARRAY($F$9), N16, $H$9:$H$307, O16) -> 6 | R16: =N16 -> 2 | S16: =O16 -> 3 | T16: =COUNTIFS(_xlfn.ANCHORARRAY($J$9), R16, $L$9:$L$307, S16) -> 10 | X16: 300 | Y16: -1.0414176
B17: 20260427_182853 | F17: 4 | G17: 4.762563 | H17: =IF(G17<0.5, 0, IF(G17<1.5, 1, IF(G17<2.5, 2, IF(G17<3.5, 3, IF(G17<4.5, 4, 5))))) -> 5 | J17: 1 | K17: 4.3758984 | L17: =IF(K17<0.5, 0, IF(K17<1.5, 1, IF(K17<2.5, 2, IF(K17<3.5, 3, IF(K17<4.5, 4, 5))))) -> 4 | N17: =N12+1 -> 2 | O17: =O12 -> 4 | P17: =COUNTIFS(_xlfn.ANCHORARRAY($F$9), N17, $H$9:$H$307, O17) -> 9 | R17: =N17 -> 2 | S17: =O17 -> 4 | T17: =COUNTIFS(_xlfn.ANCHORARRAY($J$9), R17, $L$9:$L$307, S17) -> 13 | X17: 200 | Y17: -1.0153908
B18: 20260427_183709 | F18: 4 | G18: 4.499189 | H18: =IF(G18<0.5, 0, IF(G18<1.5, 1, IF(G18<2.5, 2, IF(G18<3.5, 3, IF(G18<4.5, 4, 5))))) -> 4 | J18: 4 | K18: 2.8832324 | L18: =IF(K18<0.5, 0, IF(K18<1.5, 1, IF(K18<2.5, 2, IF(K18<3.5, 3, IF(K18<4.5, 4, 5))))) -> 3 | N18: =N13+1 -> 2 | O18: =O13 -> 5 | P18: =COUNTIFS(_xlfn.ANCHORARRAY($F$9), N18, $H$9:$H$307, O18) -> 0 | R18: =N18 -> 2 | S18: =O18 -> 5 | T18: =COUNTIFS(_xlfn.ANCHORARRAY($J$9), R18, $L$9:$L$307, S18) -> 0 | X18: 400 | Y18: -1.1813165
B19: 20260427_183734 | F19: 2 | G19: 3.660352 | H19: =IF(G19<0.5, 0, IF(G19<1.5, 1, IF(G19<2.5, 2, IF(G19<3.5, 3, IF(G19<4.5, 4, 5))))) -> 4 | J19: 2 | K19: 2.8674903 | L19: =IF(K19<0.5, 0, IF(K19<1.5, 1, IF(K19<2.5, 2, IF(K19<3.5, 3, IF(K19<4.5, 4, 5))))) -> 3 | N19: =N14+1 -> 3 | O19: =O14 -> 1 | P19: =COUNTIFS(_xlfn.ANCHORARRAY($F$9), N19, $H$9:$H$307, O19) -> 0 | R19: =N19 -> 3 | S19: =O19 -> 1 | T19: =COUNTIFS(_xlfn.ANCHORARRAY($J$9), R19, $L$9:$L$307, S19) -> 1 | X19: 400 | Y19: -1.0077115
B20: 20260427_183801 | F20: 3 | G20: 2.7960148 | H20: =IF(G20<0.5, 0, IF(G20<1.5, 1, IF(G20<2.5, 2, IF(G20<3.5, 3, IF(G20<4.5, 4, 5))))) -> 3 | J20: 5 | K20: 3.249207 | L20: =IF(K20<0.5, 0, IF(K20<1.5, 1, IF(K20<2.5, 2, IF(K20<3.5, 3, IF(K20<4.5, 4, 5))))) -> 3 | N20: =N15+1 -> 3 | O20: =O15 -> 2 | P20: =COUNTIFS(_xlfn.ANCHORARRAY($F$9), N20, $H$9:$H$307, O20) -> 5 | R20: =N20 -> 3 | S20: =O20 -> 2 | T20: =COUNTIFS(_xlfn.ANCHORARRAY($J$9), R20, $L$9:$L$307, S20) -> 1 | X20: 200 | Y20: -1.039834
B21: 20260427_183830 | F21: 1 | G21: 1.3468715 | H21: =IF(G21<0.5, 0, IF(G21<1.5, 1, IF(G21<2.5, 2, IF(G21<3.5, 3, IF(G21<4.5, 4, 5))))) -> 1 | J21: 3 | K21: 3.7178311 | L21: =IF(K21<0.5, 0, IF(K21<1.5, 1, IF(K21<2.5, 2, IF(K21<3.5, 3, IF(K21<4.5, 4, 5))))) -> 4 | N21: =N16+1 -> 3 | O21: =O16 -> 3 | P21: =COUNTIFS(_xlfn.ANCHORARRAY($F$9), N21, $H$9:$H$307, O21) -> 21 | R21: =N21 -> 3 | S21: =O21 -> 3 | T21: =COUNTIFS(_xlfn.ANCHORARRAY($J$9), R21, $L$9:$L$307, S21) -> 23 | X21: 300 | Y21: -1.0533165
B22: 20260427_215558 | F22: 3 | G22: 3.4593732 | H22: =IF(G22<0.5, 0, IF(G22<1.5, 1, IF(G22<2.5, 2, IF(G22<3.5, 3, IF(G22<4.5, 4, 5))))) -> 3 | J22: 4 | K22: 3.9525185 | L22: =IF(K22<0.5, 0, IF(K22<1.5, 1, IF(K22<2.5, 2, IF(K22<3.5, 3, IF(K22<4.5, 4, 5))))) -> 4 | N22: =N17+1 -> 3 | O22: =O17 -> 4 | P22: =COUNTIFS(_xlfn.ANCHORARRAY($F$9), N22, $H$9:$H$307, O22) -> 29 | R22: =N22 -> 3 | S22: =O22 -> 4 | T22: =COUNTIFS(_xlfn.ANCHORARRAY($J$9), R22, $L$9:$L$307, S22) -> 36 | X22: 300 | Y22: -1.0123429
B23: 20260427_222714 | F23: 5 | G23: 3.4699285 | H23: =IF(G23<0.5, 0, IF(G23<1.5, 1, IF(G23<2.5, 2, IF(G23<3.5, 3, IF(G23<4.5, 4, 5))))) -> 3 | J23: 3 | K23: 2.649782 | L23: =IF(K23<0.5, 0, IF(K23<1.5, 1, IF(K23<2.5, 2, IF(K23<3.5, 3, IF(K23<4.5, 4, 5))))) -> 3 | N23: =N18+1 -> 3 | O23: =O18 -> 5 | P23: =COUNTIFS(_xlfn.ANCHORARRAY($F$9), N23, $H$9:$H$307, O23) -> 1 | R23: =N23 -> 3 | S23: =O23 -> 5 | T23: =COUNTIFS(_xlfn.ANCHORARRAY($J$9), R23, $L$9:$L$307, S23) -> 2 | X23: 100 | Y23: -1.0318354
B24: 20260427_224837 | F24: 5 | G24: 4.1329093 | H24: =IF(G24<0.5, 0, IF(G24<1.5, 1, IF(G24<2.5, 2, IF(G24<3.5, 3, IF(G24<4.5, 4, 5))))) -> 4 | J24: 5 | K24: 4.0109262 | L24: =IF(K24<0.5, 0, IF(K24<1.5, 1, IF(K24<2.5, 2, IF(K24<3.5, 3, IF(K24<4.5, 4, 5))))) -> 4 | N24: =N19+1 -> 4 | O24: =O19 -> 1 | P24: =COUNTIFS(_xlfn.ANCHORARRAY($F$9), N24, $H$9:$H$307, O24) -> 0 | R24: =N24 -> 4 | S24: =O24 -> 1 | T24: =COUNTIFS(_xlfn.ANCHORARRAY($J$9), R24, $L$9:$L$307, S24) -> 0 | X24: 200 | Y24: -1.0010504
B25: 20260427_233525 | F25: 5 | G25: 4.5013866 | H25: =IF(G25<0.5, 0, IF(G25<1.5, 1, IF(G25<2.5, 2, IF(G25<3.5, 3, IF(G25<4.5, 4, 5))))) -> 5 | J25: 5 | K25: 4.352364 | L25: =IF(K25<0.5, 0, IF(K25<1.5, 1, IF(K25<2.5, 2, IF(K25<3.5, 3, IF(K25<4.5, 4, 5))))) -> 4 | N25: =N20+1 -> 4 | O25: =O20 -> 2 | P25: =COUNTIFS(_xlfn.ANCHORARRAY($F$9), N25, $H$9:$H$307, O25) -> 1 | R25: =N25 -> 4 | S25: =O25 -> 2 | T25: =COUNTIFS(_xlfn.ANCHORARRAY($J$9), R25, $L$9:$L$307, S25) -> 3 | X25: 400 | Y25: -1.2130898
B26: 20260428_000146 | F26: 5 | G26: 4.0105467 | H26: =IF(G26<0.5, 0, IF(G26<1.5, 1, IF(G26<2.5, 2, IF(G26<3.5, 3, IF(G26<4.5, 4, 5))))) -> 4 | J26: 5 | K26: 3.6180513 | L26: =IF(K26<0.5, 0, IF(K26<1.5, 1, IF(K26<2.5, 2, IF(K26<3.5, 3, IF(K26<4.5, 4, 5))))) -> 4 | N26: =N21+1 -> 4 | O26: =O21 -> 3 | P26: =COUNTIFS(_xlfn.ANCHORARRAY($F$9), N26, $H$9:$H$307, O26) -> 22 | R26: =N26 -> 4 | S26: =O26 -> 3 | T26: =COUNTIFS(_xlfn.ANCHORARRAY($J$9), R26, $L$9:$L$307, S26) -> 20 | X26: 300 | Y26: -1.0138762
F27: 5 | G27: 3.789383 | H27: =IF(G27<0.5, 0, IF(G27<1.5, 1, IF(G27<2.5, 2, IF(G27<3.5, 3, IF(G27<4.5, 4, 5))))) -> 4 | J27: 5 | K27: 4.6309133 | L27: =IF(K27<0.5, 0, IF(K27<1.5, 1, IF(K27<2.5, 2, IF(K27<3.5, 3, IF(K27<4.5, 4, 5))))) -> 5 | N27: =N22+1 -> 4 | O27: =O22 -> 4 | P27: =COUNTIFS(_xlfn.ANCHORARRAY($F$9), N27, $H$9:$H$307, O27) -> 70 | R27: =N27 -> 4 | S27: =O27 -> 4 | T27: =COUNTIFS(_xlfn.ANCHORARRAY($J$9), R27, $L$9:$L$307, S27) -> 61 | X27: 200 | Y27: -1.0006746
F28: 2 | G28: 2.9605904 | H28: =IF(G28<0.5, 0, IF(G28<1.5, 1, IF(G28<2.5, 2, IF(G28<3.5, 3, IF(G28<4.5, 4, 5))))) -> 3 | J28: 2 | K28: 4.233024 | L28: =IF(K28<0.5, 0, IF(K28<1.5, 1, IF(K28<2.5, 2, IF(K28<3.5, 3, IF(K28<4.5, 4, 5))))) -> 4 | N28: =N23+1 -> 4 | O28: =O23 -> 5 | P28: =COUNTIFS(_xlfn.ANCHORARRAY($F$9), N28, $H$9:$H$307, O28) -> 10 | R28: =N28 -> 4 | S28: =O28 -> 5 | T28: =COUNTIFS(_xlfn.ANCHORARRAY($J$9), R28, $L$9:$L$307, S28) -> 9 | X28: 100 | Y28: -1.0146463
F29: 5 | G29: 4.3689203 | H29: =IF(G29<0.5, 0, IF(G29<1.5, 1, IF(G29<2.5, 2, IF(G29<3.5, 3, IF(G29<4.5, 4, 5))))) -> 4 | J29: 3 | K29: 4.282786 | L29: =IF(K29<0.5, 0, IF(K29<1.5, 1, IF(K29<2.5, 2, IF(K29<3.5, 3, IF(K29<4.5, 4, 5))))) -> 4 | N29: =N24+1 -> 5 | O29: =O24 -> 1 | P29: =COUNTIFS(_xlfn.ANCHORARRAY($F$9), N29, $H$9:$H$307, O29) -> 0 | R29: =N29 -> 5 | S29: =O29 -> 1 | T29: =COUNTIFS(_xlfn.ANCHORARRAY($J$9), R29, $L$9:$L$307, S29) -> 0 | X29: 300 | Y29: -1.2660238
F30: 1 | G30: 3.0835533 | H30: =IF(G30<0.5, 0, IF(G30<1.5, 1, IF(G30<2.5, 2, IF(G30<3.5, 3, IF(G30<4.5, 4, 5))))) -> 3 | J30: 5 | K30: 4.84481 | L30: =IF(K30<0.5, 0, IF(K30<1.5, 1, IF(K30<2.5, 2, IF(K30<3.5, 3, IF(K30<4.5, 4, 5))))) -> 5 | N30: =N25+1 -> 5 | O30: =O25 -> 2 | P30: =COUNTIFS(_xlfn.ANCHORARRAY($F$9), N30, $H$9:$H$307, O30) -> 0 | R30: =N30 -> 5 | S30: =O30 -> 2 | T30: =COUNTIFS(_xlfn.ANCHORARRAY($J$9), R30, $L$9:$L$307, S30) -> 1 | X30: 300 | Y30: -1.0613868
F31: 4 | G31: 4.3013387 | H31: =IF(G31<0.5, 0, IF(G31<1.5, 1, IF(G31<2.5, 2, IF(G31<3.5, 3, IF(G31<4.5, 4, 5))))) -> 4 | J31: 5 | K31: 3.4814608 | L31: =IF(K31<0.5, 0, IF(K31<1.5, 1, IF(K31<2.5, 2, IF(K31<3.5, 3, IF(K31<4.5, 4, 5))))) -> 3 | N31: =N26+1 -> 5 | O31: =O26 -> 3 | P31: =COUNTIFS(_xlfn.ANCHORARRAY($F$9), N31, $H$9:$H$307, O31) -> 15 | R31: =N31 -> 5 | S31: =O31 -> 3 | T31: =COUNTIFS(_xlfn.ANCHORARRAY($J$9), R31, $L$9:$L$307, S31) -> 10 | X31: 200 | Y31: -1.3046751
F32: 4 | G32: 2.3461928 | H32: =IF(G32<0.5, 0, IF(G32<1.5, 1, IF(G32<2.5, 2, IF(G32<3.5, 3, IF(G32<4.5, 4, 5))))) -> 2 | J32: 3 | K32: 3.6113076 | L32: =IF(K32<0.5, 0, IF(K32<1.5, 1, IF(K32<2.5, 2, IF(K32<3.5, 3, IF(K32<4.5, 4, 5))))) -> 4 | N32: =N27+1 -> 5 | O32: =O27 -> 4 | P32: =COUNTIFS(_xlfn.ANCHORARRAY($F$9), N32, $H$9:$H$307, O32) -> 65 | R32: =N32 -> 5 | S32: =O32 -> 4 | T32: =COUNTIFS(_xlfn.ANCHORARRAY($J$9), R32, $L$9:$L$307, S32) -> 52 | X32: 100 | Y32: -1.0952619
F33: 4 | G33: 3.9366977 | H33: =IF(G33<0.5, 0, IF(G33<1.5, 1, IF(G33<2.5, 2, IF(G33<3.5, 3, IF(G33<4.5, 4, 5))))) -> 4 | J33: 5 | K33: 3.199948 | L33: =IF(K33<0.5, 0, IF(K33<1.5, 1, IF(K33<2.5, 2, IF(K33<3.5, 3, IF(K33<4.5, 4, 5))))) -> 3 | N33: =N28+1 -> 5 | O33: =O28 -> 5 | P33: =COUNTIFS(_xlfn.ANCHORARRAY($F$9), N33, $H$9:$H$307, O33) -> 12 | R33: =N33 -> 5 | S33: =O33 -> 5 | T33: =COUNTIFS(_xlfn.ANCHORARRAY($J$9), R33, $L$9:$L$307, S33) -> 20 | X33: 200 | Y33: -1.0307951
F34: 5 | G34: 4.250331 | H34: =IF(G34<0.5, 0, IF(G34<1.5, 1, IF(G34<2.5, 2, IF(G34<3.5, 3, IF(G34<4.5, 4, 5))))) -> 4 | J34: 5 | K34: 4.2574854 | L34: =IF(K34<0.5, 0, IF(K34<1.5, 1, IF(K34<2.5, 2, IF(K34<3.5, 3, IF(K34<4.5, 4, 5))))) -> 4 | X34: 100 | Y34: -1.0013433
F35: 4 | G35: 4.092302 | H35: =IF(G35<0.5, 0, IF(G35<1.5, 1, IF(G35<2.5, 2, IF(G35<3.5, 3, IF(G35<4.5, 4, 5))))) -> 4 | J35: 4 | K35: 3.39893 | L35: =IF(K35<0.5, 0, IF(K35<1.5, 1, IF(K35<2.5, 2, IF(K35<3.5, 3, IF(K35<4.5, 4, 5))))) -> 3 | X35: 400 | Y35: -1.0091326
F36: 5 | G36: 3.9137602 | H36: =IF(G36<0.5, 0, IF(G36<1.5, 1, IF(G36<2.5, 2, IF(G36<3.5, 3, IF(G36<4.5, 4, 5))))) -> 4 | J36: 4 | K36: 4.670576 | L36: =IF(K36<0.5, 0, IF(K36<1.5, 1, IF(K36<2.5, 2, IF(K36<3.5, 3, IF(K36<4.5, 4, 5))))) -> 5 | X36: 400 | Y36: -1.0011469
F37: 5 | G37: 3.9616525 | H37: =IF(G37<0.5, 0, IF(G37<1.5, 1, IF(G37<2.5, 2, IF(G37<3.5, 3, IF(G37<4.5, 4, 5))))) -> 4 | J37: 3 | K37: 3.6410792 | L37: =IF(K37<0.5, 0, IF(K37<1.5, 1, IF(K37<2.5, 2, IF(K37<3.5, 3, IF(K37<4.5, 4, 5))))) -> 4 | X37: 100 | Y37: -1.0329198
F38: 4 | G38: 3.6707826 | H38: =IF(G38<0.5, 0, IF(G38<1.5, 1, IF(G38<2.5, 2, IF(G38<3.5, 3, IF(G38<4.5, 4, 5))))) -> 4 | J38: 5 | K38: 4.158624 | L38: =IF(K38<0.5, 0, IF(K38<1.5, 1, IF(K38<2.5, 2, IF(K38<3.5, 3, IF(K38<4.5, 4, 5))))) -> 4 | X38: 100 | Y38: -1.0900534
F39: 1 | G39: 2.0759623 | H39: =IF(G39<0.5, 0, IF(G39<1.5, 1, IF(G39<2.5, 2, IF(G39<3.5, 3, IF(G39<4.5, 4, 5))))) -> 2 | J39: 2 | K39: 2.5881603 | L39: =IF(K39<0.5, 0, IF(K39<1.5, 1, IF(K39<2.5, 2, IF(K39<3.5, 3, IF(K39<4.5, 4, 5))))) -> 3 | X39: 200 | Y39: -1.0184217
F40: 5 | G40: 4.198779 | H40: =IF(G40<0.5, 0, IF(G40<1.5, 1, IF(G40<2.5, 2, IF(G40<3.5, 3, IF(G40<4.5, 4, 5))))) -> 4 | J40: 4 | K40: 3.7982762 | L40: =IF(K40<0.5, 0, IF(K40<1.5, 1, IF(K40<2.5, 2, IF(K40<3.5, 3, IF(K40<4.5, 4, 5))))) -> 4 | X40: 300 | Y40: -1.0061356
F41: 3 | G41: 2.6105745 | H41: =IF(G41<0.5, 0, IF(G41<1.5, 1, IF(G41<2.5, 2, IF(G41<3.5, 3, IF(G41<4.5, 4, 5))))) -> 3 | J41: 4 | K41: 4.040636 | L41: =IF(K41<0.5, 0, IF(K41<1.5, 1, IF(K41<2.5, 2, IF(K41<3.5, 3, IF(K41<4.5, 4, 5))))) -> 4 | X41: 300 | Y41: -1.001316
F42: 5 | G42: 4.4788103 | H42: =IF(G42<0.5, 0, IF(G42<1.5, 1, IF(G42<2.5, 2, IF(G42<3.5, 3, IF(G42<4.5, 4, 5))))) -> 4 | J42: 2 | K42: 1.6375171 | L42: =IF(K42<0.5, 0, IF(K42<1.5, 1, IF(K42<2.5, 2, IF(K42<3.5, 3, IF(K42<4.5, 4, 5))))) -> 2 | X42: 100 | Y42: -1.0113715
F43: 2 | G43: 3.9551332 | H43: =IF(G43<0.5, 0, IF(G43<1.5, 1, IF(G43<2.5, 2, IF(G43<3.5, 3, IF(G43<4.5, 4, 5))))) -> 4 | J43: 4 | K43: 3.7378812 | L43: =IF(K43<0.5, 0, IF(K43<1.5, 1, IF(K43<2.5, 2, IF(K43<3.5, 3, IF(K43<4.5, 4, 5))))) -> 4 | X43: 200 | Y43: -1.020225
F44: 5 | G44: 4.2761264 | H44: =IF(G44<0.5, 0, IF(G44<1.5, 1, IF(G44<2.5, 2, IF(G44<3.5, 3, IF(G44<4.5, 4, 5))))) -> 4 | J44: 5 | K44: 3.8854966 | L44: =IF(K44<0.5, 0, IF(K44<1.5, 1, IF(K44<2.5, 2, IF(K44<3.5, 3, IF(K44<4.5, 4, 5))))) -> 4 | X44: 300 | Y44: -1.0015428
F45: 5 | G45: 3.561304 | H45: =IF(G45<0.5, 0, IF(G45<1.5, 1, IF(G45<2.5, 2, IF(G45<3.5, 3, IF(G45<4.5, 4, 5))))) -> 4 | J45: 3 | K45: 2.8467896 | L45: =IF(K45<0.5, 0, IF(K45<1.5, 1, IF(K45<2.5, 2, IF(K45<3.5, 3, IF(K45<4.5, 4, 5))))) -> 3 | X45: 300 | Y45: -1.0038617
... F108: 3 | G108: 4.3708315 | H108: =IF(G108<0.5, 0, IF(G108<1.5, 1, IF(G108<2.5, 2, IF(G108<3.5, 3, IF(G108<4.5, 4, 5))))) -> 4 | J108: 3 | K108: 3.2839324 | L108: =IF(K108<0.5, 0, IF(K108<1.5, 1, IF(K108<2.5, 2, IF(K108<3.5, 3, IF(K108<4.5, 4, 5))))) -> 3 | X108: 100 | Y108: -1.1168829
F109: 5 | G109: 3.6456947 | H109: =IF(G109<0.5, 0, IF(G109<1.5, 1, IF(G109<2.5, 2, IF(G109<3.5, 3, IF(G109<4.5, 4, 5))))) -> 4 | J109: 5 | K109: 4.2179165 | L109: =IF(K109<0.5, 0, IF(K109<1.5, 1, IF(K109<2.5, 2, IF(K109<3.5, 3, IF(K109<4.5, 4, 5))))) -> 4
F110: 4 | G110: 4.345697 | H110: =IF(G110<0.5, 0, IF(G110<1.5, 1, IF(G110<2.5, 2, IF(G110<3.5, 3, IF(G110<4.5, 4, 5))))) -> 4 | J110: 4 | K110: 4.0628705 | L110: =IF(K110<0.5, 0, IF(K110<1.5, 1, IF(K110<2.5, 2, IF(K110<3.5, 3, IF(K110<4.5, 4, 5))))) -> 4
F111: 5 | G111: 4.139022 | H111: =IF(G111<0.5, 0, IF(G111<1.5, 1, IF(G111<2.5, 2, IF(G111<3.5, 3, IF(G111<4.5, 4, 5))))) -> 4 | J111: 3 | K111: 2.835862 | L111: =IF(K111<0.5, 0, IF(K111<1.5, 1, IF(K111<2.5, 2, IF(K111<3.5, 3, IF(K111<4.5, 4, 5))))) -> 3
F112: 5 | G112: 4.113767 | H112: =IF(G112<0.5, 0, IF(G112<1.5, 1, IF(G112<2.5, 2, IF(G112<3.5, 3, IF(G112<4.5, 4, 5))))) -> 4 | J112: 4 | K112: 3.522099 | L112: =IF(K112<0.5, 0, IF(K112<1.5, 1, IF(K112<2.5, 2, IF(K112<3.5, 3, IF(K112<4.5, 4, 5))))) -> 4
F113: 4 | G113: 4.9179835 | H113: =IF(G113<0.5, 0, IF(G113<1.5, 1, IF(G113<2.5, 2, IF(G113<3.5, 3, IF(G113<4.5, 4, 5))))) -> 5 | J113: 1 | K113: 2.8945537 | L113: =IF(K113<0.5, 0, IF(K113<1.5, 1, IF(K113<2.5, 2, IF(K113<3.5, 3, IF(K113<4.5, 4, 5))))) -> 3
F114: 1 | G114: 2.0254672 | H114: =IF(G114<0.5, 0, IF(G114<1.5, 1, IF(G114<2.5, 2, IF(G114<3.5, 3, IF(G114<4.5, 4, 5))))) -> 2 | J114: 5 | K114: 4.5659637 | L114: =IF(K114<0.5, 0, IF(K114<1.5, 1, IF(K114<2.5, 2, IF(K114<3.5, 3, IF(K114<4.5, 4, 5))))) -> 5
F115: 3 | G115: 2.967494 | H115: =IF(G115<0.5, 0, IF(G115<1.5, 1, IF(G115<2.5, 2, IF(G115<3.5, 3, IF(G115<4.5, 4, 5))))) -> 3 | J115: 3 | K115: 3.8275478 | L115: =IF(K115<0.5, 0, IF(K115<1.5, 1, IF(K115<2.5, 2, IF(K115<3.5, 3, IF(K115<4.5, 4, 5))))) -> 4
F116: 4 | G116: 4.2992334 | H116: =IF(G116<0.5, 0, IF(G116<1.5, 1, IF(G116<2.5, 2, IF(G116<3.5, 3, IF(G116<4.5, 4, 5))))) -> 4 | J116: 5 | K116: 4.12896 | L116: =IF(K116<0.5, 0, IF(K116<1.5, 1, IF(K116<2.5, 2, IF(K116<3.5, 3, IF(K116<4.5, 4, 5))))) -> 4
F117: 3 | G117: 2.8513691 | H117: =IF(G117<0.5, 0, IF(G117<1.5, 1, IF(G117<2.5, 2, IF(G117<3.5, 3, IF(G117<4.5, 4, 5))))) -> 3 | J117: 3 | K117: 4.0733104 | L117: =IF(K117<0.5, 0, IF(K117<1.5, 1, IF(K117<2.5, 2, IF(K117<3.5, 3, IF(K117<4.5, 4, 5))))) -> 4
F118: 5 | G118: 4.1671805 | H118: =IF(G118<0.5, 0, IF(G118<1.5, 1, IF(G118<2.5, 2, IF(G118<3.5, 3, IF(G118<4.5, 4, 5))))) -> 4 | J118: 5 | K118: 5.2151036 | L118: =IF(K118<0.5, 0, IF(K118<1.5, 1, IF(K118<2.5, 2, IF(K118<3.5, 3, IF(K118<4.5, 4, 5))))) -> 5
F119: 5 | G119: 4.614632 | H119: =IF(G119<0.5, 0, IF(G119<1.5, 1, IF(G119<2.5, 2, IF(G119<3.5, 3, IF(G119<4.5, 4, 5))))) -> 5 | J119: 5 | K119: 4.6579986 | L119: =IF(K119<0.5, 0, IF(K119<1.5, 1, IF(K119<2.5, 2, IF(K119<3.5, 3, IF(K119<4.5, 4, 5))))) -> 5
F120: 4 | G120: 4.046185 | H120: =IF(G120<0.5, 0, IF(G120<1.5, 1, IF(G120<2.5, 2, IF(G120<3.5, 3, IF(G120<4.5, 4, 5))))) -> 4 | J120: 3 | K120: 2.7842207 | L120: =IF(K120<0.5, 0, IF(K120<1.5, 1, IF(K120<2.5, 2, IF(K120<3.5, 3, IF(K120<4.5, 4, 5))))) -> 3
... F307: 5 | G307: 3.457445 | H307: =IF(G307<0.5, 0, IF(G307<1.5, 1, IF(G307<2.5, 2, IF(G307<3.5, 3, IF(G307<4.5, 4, 5))))) -> 3 | J307: 4 | K307: 4.551512 | L307: =IF(K307<0.5, 0, IF(K307<1.5, 1, IF(K307<2.5, 2, IF(K307<3.5, 3, IF(K307<4.5, 4, 5))))) -> 5
